{
  "w": {
    "2": {
      "y_2014": 21.67,
      "y_2015": 22.16,
      "y_2017": 22.41
    },
    "3": {
      "y_2014": 78.1,
      "y_2015": 79.38,
      "y_2017": 88.16
    },
    "4": {
      "y_2014": 10.65,
      "y_2015": 10.78,
      "y_2017": 10.89
    },
    "5": {
      "y_2014": 7.63,
      "y_2015": 7.45,
      "y_2017": 7.9
    },
    "6": {
      "y_2014": 17.75,
      "y_2015": 17.24,
      "y_2017": 18.71
    },
    "7": {
      "y_2014": null,
      "y_2015": null,
      "y_2017": null
    },
    "8": {
      "y_2014": 15.15,
      "y_2015": 18.5,
      "y_2017": 18.46
    },
    "9": {
      "y_2014": 5.83,
      "y_2015": 6.07,
      "y_2017": 6.02
    },
    "10": {
      "y_2014": 35.61,
      "y_2015": 37.35,
      "y_2017": 37.88
    },
    "11": {
      "y_2014": 25.63,
      "y_2015": 26.23,
      "y_2017": 26.51
    },
    "12": {
      "y_2014": 26.36,
      "y_2015": 26.77,
      "y_2017": 27.31
    },
    "13": {
      "y_2014": 35.51,
      "y_2015": 35.83,
      "y_2017": 35.99
    },
    "14": {
      "y_2014": 37.41,
      "y_2015": 37.84,
      "y_2017": 37.69
    },
    "15": {
      "y_2014": 20.64,
      "y_2015": 21.41,
      "y_2017": 21.79
    },
    "16": {
      "y_2014": 46.47,
      "y_2015": 47.5,
      "y_2017": 47.57
    },
    "17": {
      "y_2014": 33.62,
      "y_2015": 33.87,
      "y_2017": 33.72
    },
    "18": {
      "y_2014": 32.34,
      "y_2015": 34.33,
      "y_2017": 32.81
    },
    "19": {
      "y_2014": 35.96,
      "y_2015": 36.54,
      "y_2017": 36.58
    },
    "20": {
      "y_2014": 31.45,
      "y_2015": 31.45,
      "y_2017": 31.46
    },
    "21": {
      "y_2014": 28.9,
      "y_2015": 29.84,
      "y_2017": 30.09
    },
    "22": {
      "y_2014": 8.97,
      "y_2015": 9.61,
      "y_2017": 13.45
    },
    "23": {
      "y_2014": 10.81,
      "y_2015": 11.12,
      "y_2017": 11.11
    },
    "24": {
      "y_2014": 12.01,
      "y_2015": 11.29,
      "y_2017": 11.29
    },
    "25": {
      "y_2014": 29.58,
      "y_2015": 29.58,
      "y_2017": 29.98
    },
    "26": {
      "y_2014": 30.88,
      "y_2015": 30.96,
      "y_2017": 30.96
    },
    "27": {
      "y_2014": 27.19,
      "y_2015": 27.19,
      "y_2017": 27.21
    },
    "28": {
      "y_2014": 11.76,
      "y_2015": 11.97,
      "y_2017": 11.7
    },
    "29": {
      "y_2014": 12.4,
      "y_2015": 12.37,
      "y_2017": 12.37
    },
    "30": {
      "y_2014": 12.35,
      "y_2015": 20.91,
      "y_2017": 26.95
    },
    "31": {
      "y_2014": 16.5,
      "y_2015": 16.66,
      "y_2017": 16.8
    },
    "32": {
      "y_2014": 3.37,
      "y_2015": 3.37,
      "y_2017": 3.37
    },
    "33": {
      "y_2014": 13.2,
      "y_2015": 13.47,
      "y_2017": 13.5
    },
    "34": {
      "y_2014": 20.98,
      "y_2015": 21.77,
      "y_2017": 22.57
    },
    "35": {
      "y_2014": 16.73,
      "y_2015": 19,
      "y_2017": 22.45
    },
    "36": {
      "y_2014": 24.08,
      "y_2015": 28.54,
      "y_2017": 30.76
    },
    "37": {
      "y_2014": 17.88,
      "y_2015": 18.47,
      "y_2017": 18.89
    },
    "38": {
      "y_2014": 23.97,
      "y_2015": 23.97,
      "y_2017": 23.97
    },
    "39": {
      "y_2014": 27.16,
      "y_2015": 28.01,
      "y_2017": 29.38
    },
    "40": {
      "y_2014": 31.28,
      "y_2015": 31.71,
      "y_2017": 32.2
    },
    "41": {
      "y_2014": 15.69,
      "y_2015": 15.69,
      "y_2017": 15.71
    },
    "42": {
      "y_2014": 24.94,
      "y_2015": 25.26,
      "y_2017": 25.29
    },
    "43": {
      "y_2014": 15.14,
      "y_2015": 15.66,
      "y_2017": 15.66
    },
    "44": {
      "y_2014": 8.76,
      "y_2015": 8.99,
      "y_2017": 9.33
    },
    "45": {
      "y_2014": 30.92,
      "y_2015": 33.15,
      "y_2017": 37.49
    },
    "46": {
      "y_2014": 24.76,
      "y_2015": 24.71,
      "y_2017": 24.76
    },
    "47": {
      "y_2014": 11.7,
      "y_2015": 11.74,
      "y_2017": 10.91
    },
    "48": {
      "y_2014": 18.15,
      "y_2015": 18.34,
      "y_2017": 18.05
    },
    "49": {
      "y_2014": 25.73,
      "y_2015": 26.27,
      "y_2017": 26.7
    },
    "50": {
      "y_2014": 30.16,
      "y_2015": 30.78,
      "y_2017": 30.9
    },
    "51": {
      "y_2014": 13.68,
      "y_2015": 13.84,
      "y_2017": 14.47
    },
    "52": {
      "y_2014": 23.65,
      "y_2015": 14.57,
      "y_2017": 16.2
    },
    "53": {
      "y_2014": 29.8,
      "y_2015": 34.91,
      "y_2017": 30.35
    },
    "54": {
      "y_2014": 17.64,
      "y_2015": 17.71,
      "y_2017": 18.13
    },
    "55": {
      "y_2014": 20.01,
      "y_2015": 20.2,
      "y_2017": 20.28
    },
    "56": {
      "y_2014": 7.65,
      "y_2015": 7.75,
      "y_2017": 7.75
    },
    "57": {
      "y_2014": 15.97,
      "y_2015": 16.11,
      "y_2017": 16.38
    },
    "58": {
      "y_2014": 15.21,
      "y_2015": 15.08,
      "y_2017": 15.23
    },
    "59": {
      "y_2014": 23.83,
      "y_2015": 25.15,
      "y_2017": 26.46
    },
    "60": {
      "y_2014": 32.25,
      "y_2015": 35.44,
      "y_2017": 53.14
    },
    "61": {
      "y_2014": 11.99,
      "y_2015": 12,
      "y_2017": 12.02
    },
    "62": {
      "y_2014": null,
      "y_2015": null,
      "y_2017": null
    },
    "64": {
      "y_2014": 43.35,
      "y_2015": 44.91,
      "y_2017": 54.63
    },
    "65": {
      "y_2014": 17.77,
      "y_2015": 22.12,
      "y_2017": 22.25
    },
    "66": {
      "y_2014": 25.57,
      "y_2015": 27.25,
      "y_2017": 27.36
    },
    "67": {
      "y_2014": 5.65,
      "y_2015": 11.69,
      "y_2017": 11.48
    },
    "68": {
      "y_2014": 24.79,
      "y_2015": 24.81,
      "y_2017": 24.79
    },
    "69": {
      "y_2014": 14.54,
      "y_2015": 11.18,
      "y_2017": 13.9
    },
    "70": {
      "y_2014": 12.58,
      "y_2015": 12.77,
      "y_2017": 12.87
    },
    "71": {
      "y_2014": 41.21,
      "y_2015": 41.61,
      "y_2017": 41.67
    },
    "72": {
      "y_2014": 13.05,
      "y_2015": 27.66,
      "y_2017": 34.31
    },
    "73": {
      "y_2014": 27.8,
      "y_2015": 28.55,
      "y_2017": 29.51
    },
    "74": {
      "y_2014": 11.17,
      "y_2015": 11.39,
      "y_2017": 11.37
    },
    "75": {
      "y_2014": 17.87,
      "y_2015": 20.59,
      "y_2017": 20.49
    },
    "76": {
      "y_2014": 24.65,
      "y_2015": 31.93,
      "y_2017": 33.9
    },
    "77": {
      "y_2014": 55.33,
      "y_2015": 59.72,
      "y_2017": 59.69
    },
    "78": {
      "y_2014": 19.58,
      "y_2015": 20.52,
      "y_2017": 20.68
    },
    "79": {
      "y_2014": 22.82,
      "y_2015": 17.37,
      "y_2017": 22.8
    },
    "80": {
      "y_2014": 22.14,
      "y_2015": 21.96,
      "y_2017": 22.18
    },
    "81": {
      "y_2014": 11.76,
      "y_2015": 11.76,
      "y_2017": 12.07
    },
    "82": {
      "y_2014": 25.26,
      "y_2015": 25.26,
      "y_2017": 32.51
    },
    "83": {
      "y_2014": 8.5,
      "y_2015": 8.48,
      "y_2017": 8.78
    },
    "84": {
      "y_2014": 7.28,
      "y_2015": 6.95,
      "y_2017": 6.18
    },
    "85": {
      "y_2014": 19.65,
      "y_2015": 19.8,
      "y_2017": 19.89
    },
    "86": {
      "y_2014": 28.96,
      "y_2015": 31.29,
      "y_2017": 31.44
    },
    "87": {
      "y_2014": 16.68,
      "y_2015": 16.55,
      "y_2017": 16.64
    },
    "88": {
      "y_2014": 12.79,
      "y_2015": 12.13,
      "y_2017": 12.53
    },
    "89": {
      "y_2014": 15.02,
      "y_2015": 15.31,
      "y_2017": 15.42
    },
    "90": {
      "y_2014": 19.69,
      "y_2015": 19.97,
      "y_2017": 20.04
    },
    "91": {
      "y_2014": 23.69,
      "y_2015": 24.1,
      "y_2017": 24.24
    },
    "92": {
      "y_2014": 18.94,
      "y_2015": 23.81,
      "y_2017": 24.06
    },
    "93": {
      "y_2014": 13.53,
      "y_2015": 13.65,
      "y_2017": 13.76
    },
    "94": {
      "y_2014": 10.89,
      "y_2015": 10.98,
      "y_2017": 11.04
    },
    "95": {
      "y_2014": 16.73,
      "y_2015": 16.73,
      "y_2017": 16.73
    },
    "96": {
      "y_2014": 34.1,
      "y_2015": 42.72,
      "y_2017": 45.62
    },
    "97": {
      "y_2014": 37.82,
      "y_2015": 37.94,
      "y_2017": 38.5
    },
    "98": {
      "y_2014": 26.48,
      "y_2015": 27.39,
      "y_2017": 28.62
    },
    "99": {
      "y_2014": 15.38,
      "y_2015": 15.33,
      "y_2017": 15.75
    },
    "100": {
      "y_2014": 16.68,
      "y_2015": 17.24,
      "y_2017": 17.48
    },
    "101": {
      "y_2014": 22.84,
      "y_2015": 23.3,
      "y_2017": 23.35
    },
    "102": {
      "y_2014": 14.43,
      "y_2015": 14.74,
      "y_2017": 14.79
    },
    "103": {
      "y_2014": 15.14,
      "y_2015": 15.67,
      "y_2017": 15.56
    },
    "105": {
      "y_2014": 10.31,
      "y_2015": 13.64,
      "y_2017": 18.79
    },
    "106": {
      "y_2014": 15.79,
      "y_2015": 16.15,
      "y_2017": 16.14
    },
    "107": {
      "y_2014": 22.28,
      "y_2015": 22.28,
      "y_2017": 14.04
    },
    "108": {
      "y_2014": 14.31,
      "y_2015": 14.36,
      "y_2017": 14.36
    },
    "109": {
      "y_2014": 23.04,
      "y_2015": 24.6,
      "y_2017": 26.52
    },
    "110": {
      "y_2014": 18.6,
      "y_2015": 18.44,
      "y_2017": 18.7
    },
    "111": {
      "y_2014": 28.88,
      "y_2015": 31.94,
      "y_2017": 30.47
    },
    "112": {
      "y_2014": 13.91,
      "y_2015": 14.68,
      "y_2017": 16.9
    },
    "113": {
      "y_2014": 37.68,
      "y_2015": 40.07,
      "y_2017": 42.09
    },
    "114": {
      "y_2014": 12.1,
      "y_2015": 12.51,
      "y_2017": 15.21
    },
    "115": {
      "y_2014": 39.58,
      "y_2015": 48.49,
      "y_2017": 49.29
    },
    "116": {
      "y_2014": 35.14,
      "y_2015": 37.74,
      "y_2017": 40.53
    },
    "117": {
      "y_2014": 37.62,
      "y_2015": 39.8,
      "y_2017": 40.41
    },
    "118": {
      "y_2014": 12.04,
      "y_2015": 12.38,
      "y_2017": 12.88
    },
    "119": {
      "y_2014": 13.4,
      "y_2015": 13.54,
      "y_2017": 13.67
    },
    "120": {
      "y_2014": 14.79,
      "y_2015": 15.1,
      "y_2017": 14.93
    },
    "121": {
      "y_2014": 22.55,
      "y_2015": 22.75,
      "y_2017": 22.82
    },
    "122": {
      "y_2014": null,
      "y_2015": null,
      "y_2017": null
    },
    "123": {
      "y_2014": 25.35,
      "y_2015": 25.3,
      "y_2017": 25.52
    },
    "124": {
      "y_2014": 20.35,
      "y_2015": 20.7,
      "y_2017": 20.52
    },
    "125": {
      "y_2014": 28.41,
      "y_2015": 29.39,
      "y_2017": 33.03
    },
    "126": {
      "y_2014": 3.58,
      "y_2015": 5.39,
      "y_2017": 7.41
    },
    "127": {
      "y_2014": 23.63,
      "y_2015": 23.71,
      "y_2017": 23.96
    },
    "128": {
      "y_2014": 28.54,
      "y_2015": 28.87,
      "y_2017": 28.6
    },
    "129": {
      "y_2014": 21.83,
      "y_2015": 22.27,
      "y_2017": 22.23
    },
    "130": {
      "y_2014": 17.87,
      "y_2015": 18.08,
      "y_2017": 18.15
    },
    "131": {
      "y_2014": 19.68,
      "y_2015": 21.3,
      "y_2017": 21.63
    },
    "132": {
      "y_2014": 5.15,
      "y_2015": 5.29,
      "y_2017": 5.23
    },
    "133": {
      "y_2014": 10.7,
      "y_2015": 10.8,
      "y_2017": 10.83
    },
    "134": {
      "y_2014": 12.18,
      "y_2015": 12.52,
      "y_2017": 12.64
    },
    "135": {
      "y_2014": 12.65,
      "y_2015": 12.84,
      "y_2017": 12.66
    },
    "136": {
      "y_2014": 20.33,
      "y_2015": 20.94,
      "y_2017": 21.48
    },
    "137": {
      "y_2014": 16.98,
      "y_2015": 17.19,
      "y_2017": 17.48
    },
    "138": {
      "y_2014": 7.66,
      "y_2015": 7.65,
      "y_2017": 7.68
    },
    "139": {
      "y_2014": 16.73,
      "y_2015": 16.66,
      "y_2017": 16.81
    },
    "140": {
      "y_2014": 26.84,
      "y_2015": 29.56,
      "y_2017": 29.13
    },
    "141": {
      "y_2014": 9.9,
      "y_2015": 9.61,
      "y_2017": 9.52
    },
    "142": {
      "y_2014": 25.87,
      "y_2015": 26.35,
      "y_2017": 26.76
    },
    "143": {
      "y_2014": 13.54,
      "y_2015": 13.62,
      "y_2017": 13.57
    },
    "144": {
      "y_2014": 20.3,
      "y_2015": 21.13,
      "y_2017": 21.76
    },
    "145": {
      "y_2014": 16.67,
      "y_2015": 16.95,
      "y_2017": 17.04
    },
    "146": {
      "y_2014": 18.16,
      "y_2015": 18.67,
      "y_2017": 19.73
    },
    "147": {
      "y_2014": 22.34,
      "y_2015": 23.1,
      "y_2017": 22.39
    },
    "148": {
      "y_2014": 24.6,
      "y_2015": 24.65,
      "y_2017": 24.65
    },
    "149": {
      "y_2014": 7.65,
      "y_2015": 9.09,
      "y_2017": 9.07
    },
    "150": {
      "y_2014": 18.33,
      "y_2015": 18.45,
      "y_2017": 18.57
    },
    "151": {
      "y_2014": 34.36,
      "y_2015": 34.72,
      "y_2017": 39.68
    },
    "152": {
      "y_2014": 8.17,
      "y_2015": 8.08,
      "y_2017": 8.06
    },
    "153": {
      "y_2014": 39.08,
      "y_2015": 39.08,
      "y_2017": 39.11
    },
    "154": {
      "y_2014": 30.09,
      "y_2015": 30.06,
      "y_2017": 30.09
    },
    "155": {
      "y_2014": 26.95,
      "y_2015": 27.59,
      "y_2017": 38.61
    },
    "156": {
      "y_2014": 32.99,
      "y_2015": 35.34,
      "y_2017": 36.92
    },
    "157": {
      "y_2014": 17.37,
      "y_2015": 12.22,
      "y_2017": 12.9
    },
    "158": {
      "y_2014": 36.01,
      "y_2015": 36.58,
      "y_2017": 37.1
    },
    "159": {
      "y_2014": 10.35,
      "y_2015": 10.86,
      "y_2017": 11.84
    },
    "160": {
      "y_2014": 28.68,
      "y_2015": 29.01,
      "y_2017": 29.1
    },
    "161": {
      "y_2014": 26.27,
      "y_2015": 26.57,
      "y_2017": 27.02
    },
    "162": {
      "y_2014": 19.11,
      "y_2015": 19.4,
      "y_2017": 19.53
    },
    "163": {
      "y_2014": 8.6,
      "y_2015": 9.02,
      "y_2017": 9.01
    },
    "164": {
      "y_2014": 48.12,
      "y_2015": 46.68,
      "y_2017": 47.82
    },
    "165": {
      "y_2014": 24.21,
      "y_2015": 24.63,
      "y_2017": 24.67
    },
    "166": {
      "y_2014": 12.44,
      "y_2015": 12.68,
      "y_2017": 12.73
    },
    "167": {
      "y_2014": 7.94,
      "y_2015": 8.08,
      "y_2017": 8.07
    },
    "168": {
      "y_2014": 15.7,
      "y_2015": 15.9,
      "y_2017": 16.12
    },
    "169": {
      "y_2014": 21.14,
      "y_2015": 21.91,
      "y_2017": 25.98
    },
    "170": {
      "y_2014": 18.27,
      "y_2015": 18.33,
      "y_2017": 18.3
    },
    "171": {
      "y_2014": 9.11,
      "y_2015": 8.99,
      "y_2017": 11.46
    },
    "172": {
      "y_2014": 29.32,
      "y_2015": 30.62,
      "y_2017": 30.67
    },
    "173": {
      "y_2014": 10.74,
      "y_2015": 11.47,
      "y_2017": 12.23
    },
    "174": {
      "y_2014": 17.32,
      "y_2015": 17.23,
      "y_2017": 17.22
    },
    "175": {
      "y_2014": 18.13,
      "y_2015": 18.3,
      "y_2017": 18.26
    },
    "176": {
      "y_2014": 30.33,
      "y_2015": 30.33,
      "y_2017": 30.33
    },
    "177": {
      "y_2014": 18.49,
      "y_2015": 18.7,
      "y_2017": 18.88
    },
    "178": {
      "y_2014": 21.14,
      "y_2015": 24.31,
      "y_2017": 27.36
    },
    "179": {
      "y_2014": 16.13,
      "y_2015": 16.21,
      "y_2017": 15.96
    },
    "180": {
      "y_2014": 13,
      "y_2015": 14.46,
      "y_2017": 15.38
    },
    "181": {
      "y_2014": 27.9,
      "y_2015": 28.65,
      "y_2017": 28.83
    },
    "182": {
      "y_2014": 7.79,
      "y_2015": 7.79,
      "y_2017": 7.91
    },
    "183": {
      "y_2014": 8.48,
      "y_2015": 8.69,
      "y_2017": 8.73
    },
    "184": {
      "y_2014": 13.41,
      "y_2015": 13.69,
      "y_2017": 13.65
    },
    "185": {
      "y_2014": 29.51,
      "y_2015": 30.02,
      "y_2017": 30.74
    },
    "186": {
      "y_2014": 24.21,
      "y_2015": 24.72,
      "y_2017": 25.12
    },
    "187": {
      "y_2014": 10.04,
      "y_2015": 10.04,
      "y_2017": 10.04
    },
    "188": {
      "y_2014": 16.87,
      "y_2015": 17.2,
      "y_2017": 17.2
    },
    "189": {
      "y_2014": 10.24,
      "y_2015": 10.24,
      "y_2017": 10.24
    },
    "190": {
      "y_2014": 10.36,
      "y_2015": 10.45,
      "y_2017": 10.42
    },
    "191": {
      "y_2014": 23.35,
      "y_2015": 23.54,
      "y_2017": 23.74
    },
    "192": {
      "y_2014": 22.09,
      "y_2015": 23.9,
      "y_2017": 27.84
    },
    "193": {
      "y_2014": 13.29,
      "y_2015": 13.31,
      "y_2017": 13.28
    },
    "194": {
      "y_2014": 29.7,
      "y_2015": 29.85,
      "y_2017": 30.92
    },
    "195": {
      "y_2014": 20.9,
      "y_2015": 20.8,
      "y_2017": 29.57
    },
    "196": {
      "y_2014": 21.62,
      "y_2015": 21.95,
      "y_2017": 22.58
    },
    "197": {
      "y_2014": 25.47,
      "y_2015": 25.93,
      "y_2017": 25.96
    },
    "198": {
      "y_2014": 16.04,
      "y_2015": 16.45,
      "y_2017": 15.73
    },
    "199": {
      "y_2014": 28.38,
      "y_2015": 31.17,
      "y_2017": 31.95
    },
    "200": {
      "y_2014": 5.69,
      "y_2015": 6.04,
      "y_2017": 10.98
    },
    "201": {
      "y_2014": 29.05,
      "y_2015": 29.22,
      "y_2017": 29.29
    },
    "202": {
      "y_2014": 22.74,
      "y_2015": 23.42,
      "y_2017": 23.61
    },
    "203": {
      "y_2014": 18.19,
      "y_2015": 18.69,
      "y_2017": 20.02
    },
    "204": {
      "y_2014": 13.9,
      "y_2015": 13.9,
      "y_2017": 14.47
    },
    "205": {
      "y_2014": null,
      "y_2015": 9.42,
      "y_2017": 9.67
    },
    "206": {
      "y_2014": 13.53,
      "y_2015": 13.53,
      "y_2017": 13.5
    },
    "207": {
      "y_2014": 21.34,
      "y_2015": 25.73,
      "y_2017": 31.31
    },
    "208": {
      "y_2014": 20.59,
      "y_2015": 19.28,
      "y_2017": 21.11
    },
    "209": {
      "y_2014": 29.24,
      "y_2015": 32.04,
      "y_2017": 41.69
    },
    "210": {
      "y_2014": 18.66,
      "y_2015": 18.76,
      "y_2017": 22.36
    },
    "211": {
      "y_2014": 25.16,
      "y_2015": 25.45,
      "y_2017": 25.99
    },
    "212": {
      "y_2014": 13.72,
      "y_2015": 13.9,
      "y_2017": 13.93
    },
    "213": {
      "y_2014": 15.83,
      "y_2015": 15.91,
      "y_2017": 15.1
    },
    "215": {
      "y_2014": null,
      "y_2015": null,
      "y_2017": null
    },
    "216": {
      "y_2014": 8.09,
      "y_2015": 8.14,
      "y_2017": 7.97
    },
    "217": {
      "y_2014": 12.64,
      "y_2015": 12.94,
      "y_2017": 12.23
    },
    "218": {
      "y_2014": 26.63,
      "y_2015": 26.73,
      "y_2017": 23.34
    },
    "219": {
      "y_2014": 19.01,
      "y_2015": 19.16,
      "y_2017": 24.87
    },
    "220": {
      "y_2014": 17.51,
      "y_2015": 17.7,
      "y_2017": 17.76
    },
    "221": {
      "y_2014": 22.93,
      "y_2015": 23,
      "y_2017": 27.08
    },
    "222": {
      "y_2014": 15.79,
      "y_2015": 15.77,
      "y_2017": 15.97
    },
    "223": {
      "y_2014": 19.03,
      "y_2015": 19.27,
      "y_2017": 18.88
    },
    "224": {
      "y_2014": 23.58,
      "y_2015": 23.58,
      "y_2017": 23.58
    },
    "225": {
      "y_2014": 13.5,
      "y_2015": 13.55,
      "y_2017": 13.86
    },
    "226": {
      "y_2014": 8.65,
      "y_2015": 8.7,
      "y_2017": 8.73
    },
    "227": {
      "y_2014": 25.04,
      "y_2015": 25.46,
      "y_2017": 25.34
    },
    "228": {
      "y_2014": 5.39,
      "y_2015": 5.45,
      "y_2017": 5.45
    },
    "229": {
      "y_2014": 17.79,
      "y_2015": 21.49,
      "y_2017": 26.49
    },
    "230": {
      "y_2014": 20.71,
      "y_2015": 24.47,
      "y_2017": 24.53
    },
    "231": {
      "y_2014": 18.39,
      "y_2015": 27.75,
      "y_2017": 28.39
    },
    "232": {
      "y_2014": 25.38,
      "y_2015": 25.57,
      "y_2017": 26.98
    },
    "233": {
      "y_2014": 25.58,
      "y_2015": 25.56,
      "y_2017": 25.51
    },
    "234": {
      "y_2014": 25.51,
      "y_2015": 26.24,
      "y_2017": 26.62
    },
    "235": {
      "y_2014": 20.45,
      "y_2015": 20.61,
      "y_2017": 20.68
    },
    "236": {
      "y_2014": 10.22,
      "y_2015": 10.6,
      "y_2017": 10.58
    },
    "237": {
      "y_2014": 26.17,
      "y_2015": 27.21,
      "y_2017": 29.22
    },
    "238": {
      "y_2014": 23.51,
      "y_2015": 23.81,
      "y_2017": 23.85
    },
    "240": {
      "y_2014": 16.28,
      "y_2015": 16.39,
      "y_2017": 16.65
    },
    "241": {
      "y_2014": 18.93,
      "y_2015": 19.14,
      "y_2017": 19.24
    },
    "242": {
      "y_2014": 16.14,
      "y_2015": 16.3,
      "y_2017": 16.6
    },
    "243": {
      "y_2014": 1.26,
      "y_2015": 1.24,
      "y_2017": 1.24
    },
    "244": {
      "y_2014": 19.27,
      "y_2015": 19.27,
      "y_2017": 19.29
    },
    "245": {
      "y_2014": 14.09,
      "y_2015": 14.28,
      "y_2017": 14.37
    },
    "246": {
      "y_2014": 23.51,
      "y_2015": 23.82,
      "y_2017": 23.96
    },
    "247": {
      "y_2014": 11.26,
      "y_2015": 11.44,
      "y_2017": 11.56
    },
    "248": {
      "y_2014": 17.83,
      "y_2015": 18.06,
      "y_2017": 18.17
    },
    "249": {
      "y_2014": 16.37,
      "y_2015": 16.65,
      "y_2017": 16.68
    },
    "250": {
      "y_2014": 17.14,
      "y_2015": 17.19,
      "y_2017": 17.19
    },
    "251": {
      "y_2014": 16.86,
      "y_2015": 18.15,
      "y_2017": 18.4
    },
    "252": {
      "y_2014": 10.42,
      "y_2015": 10.41,
      "y_2017": 10.46
    },
    "253": {
      "y_2014": 20.5,
      "y_2015": 20.52,
      "y_2017": 20.52
    },
    "254": {
      "y_2014": 5.46,
      "y_2015": 5.42,
      "y_2017": 10.32
    },
    "255": {
      "y_2014": 28.95,
      "y_2015": 28.95,
      "y_2017": 28.95
    },
    "256": {
      "y_2014": 27.9,
      "y_2015": 30.45,
      "y_2017": 36.91
    },
    "257": {
      "y_2014": 32.18,
      "y_2015": 36.06,
      "y_2017": 40.41
    },
    "258": {
      "y_2014": 29.03,
      "y_2015": 30.64,
      "y_2017": 33.33
    },
    "259": {
      "y_2014": 24.78,
      "y_2015": 24.92,
      "y_2017": 24.98
    },
    "260": {
      "y_2014": 37.23,
      "y_2015": 37.44,
      "y_2017": 37.64
    },
    "261": {
      "y_2014": 23.48,
      "y_2015": 23.48,
      "y_2017": 23.51
    },
    "262": {
      "y_2014": 32.16,
      "y_2015": 32.16,
      "y_2017": 32.18
    },
    "263": {
      "y_2014": 25.75,
      "y_2015": 26.36,
      "y_2017": 26.73
    },
    "264": {
      "y_2014": 19.96,
      "y_2015": 20.85,
      "y_2017": 21.42
    },
    "265": {
      "y_2014": 14.95,
      "y_2015": 14.96,
      "y_2017": 14.99
    },
    "266": {
      "y_2014": 28.7,
      "y_2015": 28.7,
      "y_2017": 30.22
    },
    "267": {
      "y_2014": 44,
      "y_2015": 45.86,
      "y_2017": 47.24
    },
    "268": {
      "y_2014": 17.57,
      "y_2015": 17.88,
      "y_2017": 18
    },
    "269": {
      "y_2014": 27.74,
      "y_2015": 27.91,
      "y_2017": 28.02
    },
    "270": {
      "y_2014": 13.68,
      "y_2015": 13.87,
      "y_2017": 13.95
    },
    "271": {
      "y_2014": 11.68,
      "y_2015": 12.07,
      "y_2017": 12.25
    },
    "272": {
      "y_2014": 14.5,
      "y_2015": 14.5,
      "y_2017": 14.5
    },
    "273": {
      "y_2014": 17.9,
      "y_2015": 18.73,
      "y_2017": 18.82
    },
    "274": {
      "y_2014": 10.39,
      "y_2015": 10.52,
      "y_2017": 10.49
    },
    "275": {
      "y_2014": 21.11,
      "y_2015": 21.18,
      "y_2017": 21.13
    },
    "276": {
      "y_2014": 19.71,
      "y_2015": 19.71,
      "y_2017": 19.74
    },
    "277": {
      "y_2014": 15.26,
      "y_2015": 18.02,
      "y_2017": 21.46
    },
    "278": {
      "y_2014": 16,
      "y_2015": 16.02,
      "y_2017": 16.02
    },
    "279": {
      "y_2014": 15.05,
      "y_2015": 15.05,
      "y_2017": 15.05
    },
    "280": {
      "y_2014": 12.53,
      "y_2015": 12.76,
      "y_2017": 12.76
    },
    "281": {
      "y_2014": 10.67,
      "y_2015": 10.67,
      "y_2017": 10.67
    },
    "282": {
      "y_2014": 14.04,
      "y_2015": 14.52,
      "y_2017": 15.44
    },
    "283": {
      "y_2014": 26.17,
      "y_2015": 26.56,
      "y_2017": 26.68
    },
    "284": {
      "y_2014": 9.68,
      "y_2015": 9.6,
      "y_2017": 9.85
    },
    "285": {
      "y_2014": null,
      "y_2015": null,
      "y_2017": null
    },
    "286": {
      "y_2014": null,
      "y_2015": null,
      "y_2017": null
    },
    "287": {
      "y_2014": 22.95,
      "y_2015": 24.01,
      "y_2017": 23.66
    },
    "288": {
      "y_2014": 22.16,
      "y_2015": 22.5,
      "y_2017": 22.57
    },
    "289": {
      "y_2014": 36.55,
      "y_2015": 36.64,
      "y_2017": 37.26
    },
    "290": {
      "y_2014": 5.32,
      "y_2015": 9.83,
      "y_2017": 9.73
    },
    "291": {
      "y_2014": 26.49,
      "y_2015": 27.43,
      "y_2017": 27.18
    },
    "292": {
      "y_2014": 11.71,
      "y_2015": 11.36,
      "y_2017": 11.3
    },
    "293": {
      "y_2014": 8.44,
      "y_2015": 8.22,
      "y_2017": 8.91
    },
    "294": {
      "y_2014": 9.92,
      "y_2015": 10.04,
      "y_2017": 11.2
    },
    "295": {
      "y_2014": 14.27,
      "y_2015": 14.22,
      "y_2017": 14.16
    },
    "296": {
      "y_2014": 13.56,
      "y_2015": 15.7,
      "y_2017": 19.1
    },
    "297": {
      "y_2014": 4.41,
      "y_2015": 4.5,
      "y_2017": null
    },
    "298": {
      "y_2014": 15.11,
      "y_2015": 15.1,
      "y_2017": 15.24
    },
    "299": {
      "y_2014": 30.12,
      "y_2015": 30.76,
      "y_2017": 33.03
    },
    "300": {
      "y_2014": 10.86,
      "y_2015": 10.85,
      "y_2017": 10.94
    },
    "301": {
      "y_2014": 21.13,
      "y_2015": 22.49,
      "y_2017": 23.86
    },
    "302": {
      "y_2014": 29.44,
      "y_2015": 29.94,
      "y_2017": 29.74
    },
    "303": {
      "y_2014": 17.85,
      "y_2015": 18.04,
      "y_2017": 18.07
    },
    "304": {
      "y_2014": 12.1,
      "y_2015": 12.36,
      "y_2017": 12.41
    },
    "305": {
      "y_2014": 8.82,
      "y_2015": 8.96,
      "y_2017": 8.94
    },
    "306": {
      "y_2014": 9.81,
      "y_2015": 13.34,
      "y_2017": 17.21
    },
    "307": {
      "y_2014": 29.48,
      "y_2015": 29.72,
      "y_2017": 39.09
    },
    "308": {
      "y_2014": 11.52,
      "y_2015": 12.67,
      "y_2017": 12.67
    },
    "309": {
      "y_2014": 17.32,
      "y_2015": 17.82,
      "y_2017": 18.05
    },
    "310": {
      "y_2014": 22.09,
      "y_2015": 22.19,
      "y_2017": 22.28
    },
    "311": {
      "y_2014": 12.43,
      "y_2015": 12.17,
      "y_2017": 12.4
    },
    "312": {
      "y_2014": 17.48,
      "y_2015": 17.76,
      "y_2017": 17.75
    },
    "313": {
      "y_2014": 16.68,
      "y_2015": 16.68,
      "y_2017": 16.68
    },
    "314": {
      "y_2014": 26.45,
      "y_2015": 26.51,
      "y_2017": 26.18
    },
    "315": {
      "y_2014": 6.11,
      "y_2015": 7.41,
      "y_2017": 7.59
    },
    "316": {
      "y_2014": 43.01,
      "y_2015": 42.64,
      "y_2017": 43.07
    },
    "317": {
      "y_2014": 7.84,
      "y_2015": 7.98,
      "y_2017": 8.06
    },
    "318": {
      "y_2014": 16.61,
      "y_2015": 16.6,
      "y_2017": 18.5
    },
    "319": {
      "y_2014": 30.95,
      "y_2015": 33.05,
      "y_2017": 32.94
    },
    "320": {
      "y_2014": 10.77,
      "y_2015": 10.67,
      "y_2017": 9.89
    },
    "321": {
      "y_2014": 11.49,
      "y_2015": 11.86,
      "y_2017": 11.98
    },
    "322": {
      "y_2014": 11.47,
      "y_2015": 12.09,
      "y_2017": 12.71
    },
    "323": {
      "y_2014": 24.52,
      "y_2015": 26.02,
      "y_2017": 26.16
    },
    "324": {
      "y_2014": 16.58,
      "y_2015": 16.61,
      "y_2017": 16.69
    },
    "325": {
      "y_2014": 26.88,
      "y_2015": 27.56,
      "y_2017": 27.86
    },
    "326": {
      "y_2014": 9.38,
      "y_2015": 9.59,
      "y_2017": 9.6
    },
    "327": {
      "y_2014": 16.85,
      "y_2015": 17.08,
      "y_2017": 17.2
    },
    "328": {
      "y_2014": 10.93,
      "y_2015": 10.99,
      "y_2017": 10.96
    },
    "329": {
      "y_2014": 20.57,
      "y_2015": 20.63,
      "y_2017": 20.82
    },
    "330": {
      "y_2014": 21.17,
      "y_2015": 21.49,
      "y_2017": 22.47
    },
    "331": {
      "y_2014": 16.07,
      "y_2015": 16.17,
      "y_2017": 16.53
    },
    "332": {
      "y_2014": 16.3,
      "y_2015": 17.69,
      "y_2017": 18.71
    },
    "333": {
      "y_2014": 28.83,
      "y_2015": 29.59,
      "y_2017": 30.65
    },
    "334": {
      "y_2014": 7.38,
      "y_2015": 7.42,
      "y_2017": 7.44
    },
    "335": {
      "y_2014": 31.41,
      "y_2015": 33.24,
      "y_2017": 33.98
    },
    "336": {
      "y_2014": 46.12,
      "y_2015": 48.96,
      "y_2017": 50.04
    },
    "337": {
      "y_2014": 19.34,
      "y_2015": 19.39,
      "y_2017": 20.5
    },
    "338": {
      "y_2014": 17.39,
      "y_2015": 22.16,
      "y_2017": 21.67
    },
    "339": {
      "y_2014": 12.18,
      "y_2015": 15.75,
      "y_2017": 19.18
    },
    "340": {
      "y_2014": 65.44,
      "y_2015": 67.89,
      "y_2017": 67.33
    },
    "341": {
      "y_2014": 40.62,
      "y_2015": 43.55,
      "y_2017": 44.82
    },
    "342": {
      "y_2014": 5.23,
      "y_2015": 6.31,
      "y_2017": null
    },
    "343": {
      "y_2014": 17.28,
      "y_2015": 16.18,
      "y_2017": 16.43
    },
    "344": {
      "y_2014": 14.86,
      "y_2015": 16.4,
      "y_2017": 17.71
    },
    "345": {
      "y_2014": 9.27,
      "y_2015": 9.33,
      "y_2017": 9.39
    },
    "346": {
      "y_2014": 28.11,
      "y_2015": 28.5,
      "y_2017": 28.91
    },
    "347": {
      "y_2014": 6.6,
      "y_2015": 8.64,
      "y_2017": 8.71
    },
    "348": {
      "y_2014": 31.7,
      "y_2015": 32,
      "y_2017": 32.4
    },
    "349": {
      "y_2014": 20.02,
      "y_2015": 20.3,
      "y_2017": 16.21
    },
    "350": {
      "y_2014": 15.59,
      "y_2015": 15.81,
      "y_2017": 15.01
    },
    "351": {
      "y_2014": 10.93,
      "y_2015": 12.01,
      "y_2017": 12.26
    },
    "352": {
      "y_2014": 24.99,
      "y_2015": 25.01,
      "y_2017": 25.01
    },
    "353": {
      "y_2014": 25.52,
      "y_2015": 26.1,
      "y_2017": 26.05
    },
    "354": {
      "y_2014": 17.91,
      "y_2015": 17.91,
      "y_2017": 17.91
    },
    "355": {
      "y_2014": 21.19,
      "y_2015": 21.19,
      "y_2017": 21.19
    },
    "356": {
      "y_2014": 48.06,
      "y_2015": 48.25,
      "y_2017": 48.52
    },
    "357": {
      "y_2014": 25.83,
      "y_2015": 26.87,
      "y_2017": 27.01
    },
    "358": {
      "y_2014": 31.73,
      "y_2015": 32.03,
      "y_2017": 29.91
    },
    "359": {
      "y_2014": 22.45,
      "y_2015": 22.52,
      "y_2017": 22.56
    },
    "360": {
      "y_2014": 42.3,
      "y_2015": 43.96,
      "y_2017": 44.32
    },
    "361": {
      "y_2014": 11.24,
      "y_2015": 11.4,
      "y_2017": 19.03
    },
    "362": {
      "y_2014": 30.89,
      "y_2015": 31.84,
      "y_2017": 31.59
    },
    "363": {
      "y_2014": 29.12,
      "y_2015": 29.67,
      "y_2017": 29.63
    },
    "364": {
      "y_2014": 27.45,
      "y_2015": 28.52,
      "y_2017": 28.75
    },
    "365": {
      "y_2014": 16.57,
      "y_2015": 16.86,
      "y_2017": 17
    },
    "366": {
      "y_2014": 7.38,
      "y_2015": 7.96,
      "y_2017": 7.84
    },
    "367": {
      "y_2014": 44.69,
      "y_2015": 48.66,
      "y_2017": 55.56
    },
    "368": {
      "y_2014": 30.38,
      "y_2015": 30.38,
      "y_2017": 30.38
    },
    "369": {
      "y_2014": 12.69,
      "y_2015": 10.22,
      "y_2017": 11.09
    },
    "370": {
      "y_2014": 31.34,
      "y_2015": 32.18,
      "y_2017": 32.74
    },
    "371": {
      "y_2014": 57.65,
      "y_2015": 59.76,
      "y_2017": 60.56
    },
    "372": {
      "y_2014": 117.45,
      "y_2015": 117.79,
      "y_2017": 119.19
    },
    "373": {
      "y_2014": 25,
      "y_2015": 25.13,
      "y_2017": 25.5
    },
    "374": {
      "y_2014": 24.83,
      "y_2015": 24.87,
      "y_2017": 25.57
    },
    "375": {
      "y_2014": 23.71,
      "y_2015": 24.01,
      "y_2017": 24.07
    },
    "376": {
      "y_2014": 39.4,
      "y_2015": 39.95,
      "y_2017": 41.55
    },
    "377": {
      "y_2014": 55.1,
      "y_2015": 55.95,
      "y_2017": 57.69
    },
    "378": {
      "y_2014": 42.33,
      "y_2015": 43.5,
      "y_2017": 43.84
    },
    "379": {
      "y_2014": 41.6,
      "y_2015": 42.02,
      "y_2017": 42.93
    },
    "380": {
      "y_2014": 57,
      "y_2015": 57.26,
      "y_2017": 57.39
    },
    "381": {
      "y_2014": 30.71,
      "y_2015": 30.92,
      "y_2017": 35.47
    },
    "382": {
      "y_2014": 30.15,
      "y_2015": 30.5,
      "y_2017": 30.05
    },
    "383": {
      "y_2014": 40.77,
      "y_2015": 40.93,
      "y_2017": 41.4
    },
    "384": {
      "y_2014": 31.22,
      "y_2015": 36.61,
      "y_2017": 48.44
    },
    "385": {
      "y_2014": 43.71,
      "y_2015": 48.11,
      "y_2017": 49.27
    },
    "386": {
      "y_2014": 18.98,
      "y_2015": 19.55,
      "y_2017": 19.2
    },
    "387": {
      "y_2014": 22.82,
      "y_2015": 23.27,
      "y_2017": 23.07
    },
    "388": {
      "y_2014": 17.28,
      "y_2015": 20.53,
      "y_2017": 30.45
    },
    "389": {
      "y_2014": 88.26,
      "y_2015": 93.59,
      "y_2017": 93.71
    },
    "390": {
      "y_2014": 14.75,
      "y_2015": 14.68,
      "y_2017": 15.02
    },
    "391": {
      "y_2014": 22.84,
      "y_2015": 23.48,
      "y_2017": 23.51
    },
    "392": {
      "y_2014": 100.51,
      "y_2015": 102.59,
      "y_2017": 101.97
    },
    "393": {
      "y_2014": 59.17,
      "y_2015": 57.88,
      "y_2017": 54.77
    },
    "394": {
      "y_2014": 28.82,
      "y_2015": 29.35,
      "y_2017": 29.3
    },
    "395": {
      "y_2014": 15.68,
      "y_2015": 15.8,
      "y_2017": 15.83
    },
    "396": {
      "y_2014": 26.7,
      "y_2015": 27.37,
      "y_2017": 28.85
    },
    "397": {
      "y_2014": 15.66,
      "y_2015": 18.46,
      "y_2017": 19.16
    },
    "398": {
      "y_2014": 5.88,
      "y_2015": 6.43,
      "y_2017": 6.87
    },
    "399": {
      "y_2014": 20.21,
      "y_2015": 20.31,
      "y_2017": 21.27
    },
    "400": {
      "y_2014": 25.26,
      "y_2015": 25.28,
      "y_2017": 25.34
    },
    "401": {
      "y_2014": 21.84,
      "y_2015": 21.89,
      "y_2017": 21.89
    },
    "402": {
      "y_2014": 15.96,
      "y_2015": 15.84,
      "y_2017": 15.84
    },
    "403": {
      "y_2014": 17.41,
      "y_2015": 19.27,
      "y_2017": 20.04
    },
    "404": {
      "y_2014": 20.81,
      "y_2015": 20.69,
      "y_2017": 20.79
    },
    "405": {
      "y_2014": 34.6,
      "y_2015": 34.74,
      "y_2017": 34.75
    },
    "406": {
      "y_2014": 20,
      "y_2015": 21.46,
      "y_2017": 23.23
    },
    "407": {
      "y_2014": 18.44,
      "y_2015": 18.69,
      "y_2017": 19.2
    },
    "408": {
      "y_2014": 26.9,
      "y_2015": 27.13,
      "y_2017": 27.3
    },
    "409": {
      "y_2014": 27.72,
      "y_2015": 28.26,
      "y_2017": 28.54
    },
    "410": {
      "y_2014": 17.2,
      "y_2015": 17.18,
      "y_2017": 17.18
    },
    "411": {
      "y_2014": 15.46,
      "y_2015": 15.61,
      "y_2017": 15.56
    },
    "412": {
      "y_2014": 6.54,
      "y_2015": 6.67,
      "y_2017": 6.75
    },
    "413": {
      "y_2014": 38.05,
      "y_2015": 38.36,
      "y_2017": 38.39
    },
    "416": {
      "y_2014": 16.25,
      "y_2015": 16.25,
      "y_2017": 16.25
    },
    "417": {
      "y_2014": 19.8,
      "y_2015": 19.8,
      "y_2017": 23.88
    },
    "418": {
      "y_2014": 33.09,
      "y_2015": 33.09,
      "y_2017": 33.09
    },
    "419": {
      "y_2014": 30.94,
      "y_2015": 30.97,
      "y_2017": 30.97
    },
    "420": {
      "y_2014": 26.44,
      "y_2015": 27.21,
      "y_2017": 27.45
    },
    "421": {
      "y_2014": 13.92,
      "y_2015": 16.07,
      "y_2017": 18.19
    },
    "422": {
      "y_2014": 15.2,
      "y_2015": 21.33,
      "y_2017": 23.11
    },
    "423": {
      "y_2014": 20.42,
      "y_2015": 20.75,
      "y_2017": 23.39
    },
    "424": {
      "y_2014": 16.9,
      "y_2015": 16.89,
      "y_2017": 16.98
    },
    "425": {
      "y_2014": 12.04,
      "y_2015": 12.11,
      "y_2017": 12.72
    },
    "426": {
      "y_2014": 20.47,
      "y_2015": 20.45,
      "y_2017": 20.42
    },
    "428": {
      "y_2014": 14.31,
      "y_2015": 15.03,
      "y_2017": 16.01
    },
    "430": {
      "y_2014": 28.21,
      "y_2015": 29.62,
      "y_2017": 31.46
    },
    "431": {
      "y_2014": 18.12,
      "y_2015": 18.34,
      "y_2017": 18.75
    },
    "432": {
      "y_2014": 25.58,
      "y_2015": 26.07,
      "y_2017": 26.67
    },
    "433": {
      "y_2014": 10.04,
      "y_2015": 10.04,
      "y_2017": 10.11
    },
    "434": {
      "y_2014": 28.45,
      "y_2015": 31.91,
      "y_2017": 34.34
    },
    "435": {
      "y_2014": 5.68,
      "y_2015": 6.07,
      "y_2017": 6.34
    },
    "436": {
      "y_2014": 15.98,
      "y_2015": 16.02,
      "y_2017": 16.12
    },
    "437": {
      "y_2014": 24.73,
      "y_2015": 29.51,
      "y_2017": 33.11
    },
    "438": {
      "y_2014": 12.45,
      "y_2015": 19.57,
      "y_2017": 26.85
    },
    "442": {
      "y_2014": 19.8,
      "y_2015": 20.17,
      "y_2017": 20.88
    },
    "443": {
      "y_2014": 17.09,
      "y_2015": 17.13,
      "y_2017": 17.1
    },
    "444": {
      "y_2014": 22.26,
      "y_2015": 22.38,
      "y_2017": 22.71
    },
    "445": {
      "y_2014": 29.38,
      "y_2015": 29.35,
      "y_2017": 29.38
    },
    "446": {
      "y_2014": 13.08,
      "y_2015": 13.62,
      "y_2017": 14.52
    },
    "447": {
      "y_2014": 23.56,
      "y_2015": 24.14,
      "y_2017": 26.39
    },
    "448": {
      "y_2014": 27.81,
      "y_2015": 31.62,
      "y_2017": 33.58
    },
    "449": {
      "y_2014": 23.42,
      "y_2015": 23.47,
      "y_2017": 23.5
    },
    "450": {
      "y_2014": 37.54,
      "y_2015": 39.78,
      "y_2017": 41.1
    },
    "451": {
      "y_2014": null,
      "y_2015": null,
      "y_2017": null
    },
    "452": {
      "y_2014": 16.19,
      "y_2015": 16.9,
      "y_2017": 16.95
    },
    "453": {
      "y_2014": 20.05,
      "y_2015": 20.05,
      "y_2017": 20.03
    },
    "454": {
      "y_2014": 15.18,
      "y_2015": 15.12,
      "y_2017": 15.14
    },
    "455": {
      "y_2014": 19.88,
      "y_2015": 19.88,
      "y_2017": 22.52
    },
    "456": {
      "y_2014": 10.98,
      "y_2015": 10.87,
      "y_2017": 8.65
    },
    "457": {
      "y_2014": 10.58,
      "y_2015": 10.55,
      "y_2017": 10.61
    },
    "458": {
      "y_2014": 11.27,
      "y_2015": 11.26,
      "y_2017": 11.27
    },
    "459": {
      "y_2014": 27.79,
      "y_2015": 27.79,
      "y_2017": 27.79
    },
    "460": {
      "y_2014": 29.61,
      "y_2015": 30.03,
      "y_2017": 29.97
    },
    "462": {
      "y_2014": 20.28,
      "y_2015": 21.35,
      "y_2017": 24.12
    },
    "463": {
      "y_2014": 23.75,
      "y_2015": 23.91,
      "y_2017": 25.52
    },
    "464": {
      "y_2014": 35.17,
      "y_2015": 35.64,
      "y_2017": 40.12
    },
    "465": {
      "y_2014": 12.52,
      "y_2015": 12.52,
      "y_2017": 12.52
    },
    "466": {
      "y_2014": 25.19,
      "y_2015": 25.62,
      "y_2017": 26.11
    },
    "467": {
      "y_2014": 21.58,
      "y_2015": 21.61,
      "y_2017": 21.68
    },
    "468": {
      "y_2014": null,
      "y_2015": null,
      "y_2017": null
    },
    "469": {
      "y_2014": null,
      "y_2015": null,
      "y_2017": null
    },
    "470": {
      "y_2014": 23.38,
      "y_2015": 23.36,
      "y_2017": 23.43
    },
    "471": {
      "y_2014": 27.77,
      "y_2015": 27.71,
      "y_2017": 27.73
    },
    "472": {
      "y_2014": 12.9,
      "y_2015": 13.1,
      "y_2017": 13.37
    },
    "473": {
      "y_2014": null,
      "y_2015": null,
      "y_2017": null
    },
    "474": {
      "y_2014": 23.82,
      "y_2015": 23.9,
      "y_2017": 24.02
    },
    "475": {
      "y_2014": null,
      "y_2015": null,
      "y_2017": null
    }
  },
  "map": {
    "2": {
      "y_2014": 13.4287,
      "y_2015": 18.1408,
      "y_2017": 15.4395
    },
    "3": {
      "y_2014": 8.3739,
      "y_2015": 3.8675,
      "y_2017": 5.887
    },
    "4": {
      "y_2014": 0.5634,
      "y_2015": 0.8349,
      "y_2017": 1.1938
    },
    "5": {
      "y_2014": 38.27,
      "y_2015": 53.0201,
      "y_2017": 43.038
    },
    "6": {
      "y_2014": 34.9859,
      "y_2015": 47.9118,
      "y_2017": 37.6269
    },
    "7": {
      "y_2014": null,
      "y_2015": null,
      "y_2017": null
    },
    "8": {
      "y_2014": 20,
      "y_2015": 9.4054,
      "y_2017": 12.6219
    },
    "9": {
      "y_2014": 6.8611,
      "y_2015": 9.5552,
      "y_2017": 10.6312
    },
    "10": {
      "y_2014": 29.0649,
      "y_2015": 29.1566,
      "y_2017": 28.9335
    },
    "11": {
      "y_2014": 1.2095,
      "y_2015": 1.4868,
      "y_2017": 1.2448
    },
    "12": {
      "y_2014": 27.2762,
      "y_2015": 34.3668,
      "y_2017": 30.5016
    },
    "13": {
      "y_2014": 15.4604,
      "y_2015": 18.2529,
      "y_2017": 15.5321
    },
    "14": {
      "y_2014": 10.1844,
      "y_2015": 16.3319,
      "y_2017": 14.0886
    },
    "15": {
      "y_2014": 4.5058,
      "y_2015": 5.5114,
      "y_2017": 5.0023
    },
    "16": {
      "y_2014": 22.3585,
      "y_2015": 31.4316,
      "y_2017": 28.8207
    },
    "17": {
      "y_2014": 27.8406,
      "y_2015": 35.9906,
      "y_2017": 30.1601
    },
    "18": {
      "y_2014": 3.8343,
      "y_2015": 3.7868,
      "y_2017": 3.7793
    },
    "19": {
      "y_2014": 2.4194,
      "y_2015": 4.6798,
      "y_2017": 3.9092
    },
    "20": {
      "y_2014": 3.4022,
      "y_2015": 5.1828,
      "y_2017": 4.3865
    },
    "21": {
      "y_2014": 32.3529,
      "y_2015": 36.6287,
      "y_2017": 30.2426
    },
    "22": {
      "y_2014": 12.0401,
      "y_2015": 14.6722,
      "y_2017": 9.9628
    },
    "23": {
      "y_2014": 44.7734,
      "y_2015": 49.5504,
      "y_2017": 49.2349
    },
    "24": {
      "y_2014": 13.1557,
      "y_2015": 12.0461,
      "y_2017": 7.3516
    },
    "25": {
      "y_2014": 2.4341,
      "y_2015": 4.0906,
      "y_2017": 3.469
    },
    "26": {
      "y_2014": 6.5415,
      "y_2015": 10.4974,
      "y_2017": 8.3979
    },
    "27": {
      "y_2014": 19.8235,
      "y_2015": 22.7657,
      "y_2017": 18.7064
    },
    "28": {
      "y_2014": 1.6156,
      "y_2015": 1.3367,
      "y_2017": 2.8205
    },
    "29": {
      "y_2014": 2.3387,
      "y_2015": 4.6079,
      "y_2017": 3.9612
    },
    "30": {
      "y_2014": 56.3563,
      "y_2015": 44.8589,
      "y_2017": 32.4675
    },
    "31": {
      "y_2014": 1.2121,
      "y_2015": 1.5606,
      "y_2017": 1.8452
    },
    "32": {
      "y_2014": 7.1217,
      "y_2015": 6.5282,
      "y_2017": 7.4184
    },
    "33": {
      "y_2014": 6.3636,
      "y_2015": 12.0267,
      "y_2017": 7.5556
    },
    "34": {
      "y_2014": 24.4519,
      "y_2015": 32.1084,
      "y_2017": 30.1728
    },
    "35": {
      "y_2014": 15.3019,
      "y_2015": 20.7368,
      "y_2017": 15.2784
    },
    "36": {
      "y_2014": 8.2226,
      "y_2015": 9.2852,
      "y_2017": 7.7048
    },
    "37": {
      "y_2014": 35.3468,
      "y_2015": 36.275,
      "y_2017": 32.0275
    },
    "38": {
      "y_2014": 4.6308,
      "y_2015": 6.5499,
      "y_2017": 5.6738
    },
    "39": {
      "y_2014": 15.9057,
      "y_2015": 26.5262,
      "y_2017": 18.8564
    },
    "40": {
      "y_2014": 22.8261,
      "y_2015": 32.6395,
      "y_2017": 28.0435
    },
    "41": {
      "y_2014": 8.6042,
      "y_2015": 13.5755,
      "y_2017": 12.2852
    },
    "42": {
      "y_2014": 5.1724,
      "y_2015": 6.4925,
      "y_2017": 5.694
    },
    "43": {
      "y_2014": 9.1149,
      "y_2015": 8.6845,
      "y_2017": 5.8748
    },
    "44": {
      "y_2014": 1.0274,
      "y_2015": 2.8921,
      "y_2017": 3.8585
    },
    "45": {
      "y_2014": 5.8538,
      "y_2015": 7.6923,
      "y_2017": 6.5351
    },
    "46": {
      "y_2014": 11.5913,
      "y_2015": 17.4423,
      "y_2017": 16.2359
    },
    "47": {
      "y_2014": 7.3504,
      "y_2015": 6.3884,
      "y_2017": 9.7159
    },
    "48": {
      "y_2014": 21.4325,
      "y_2015": 26.7721,
      "y_2017": 21.662
    },
    "49": {
      "y_2014": 12.6312,
      "y_2015": 21.0506,
      "y_2017": 17.3783
    },
    "50": {
      "y_2014": 41.6114,
      "y_2015": 49.5127,
      "y_2017": 38.6084
    },
    "51": {
      "y_2014": 6.3596,
      "y_2015": 8.1647,
      "y_2017": 6.0124
    },
    "52": {
      "y_2014": 25.666,
      "y_2015": 37.8861,
      "y_2017": 29.1975
    },
    "53": {
      "y_2014": 32.1812,
      "y_2015": 35.2621,
      "y_2017": 32.2241
    },
    "54": {
      "y_2014": 28.9683,
      "y_2015": 36.0248,
      "y_2017": 28.075
    },
    "55": {
      "y_2014": 6.1469,
      "y_2015": 8.8614,
      "y_2017": 6.213
    },
    "56": {
      "y_2014": 7.8431,
      "y_2015": 11.0968,
      "y_2017": 9.0323
    },
    "57": {
      "y_2014": 33.9386,
      "y_2015": 47.7964,
      "y_2017": 34.0049
    },
    "58": {
      "y_2014": 27.8764,
      "y_2015": 41.1804,
      "y_2017": 32.042
    },
    "59": {
      "y_2014": 32.3542,
      "y_2015": 29.1849,
      "y_2017": 28.1557
    },
    "60": {
      "y_2014": 10.6357,
      "y_2015": 13.4876,
      "y_2017": 8.2236
    },
    "61": {
      "y_2014": 8.2569,
      "y_2015": 16.6667,
      "y_2017": 14.6423
    },
    "62": {
      "y_2014": null,
      "y_2015": null,
      "y_2017": null
    },
    "64": {
      "y_2014": 11.2111,
      "y_2015": 14.8742,
      "y_2017": 10.2142
    },
    "65": {
      "y_2014": 2.9263,
      "y_2015": 4.4304,
      "y_2017": 5.4382
    },
    "66": {
      "y_2014": 15.6433,
      "y_2015": 11.5596,
      "y_2017": 14.2909
    },
    "67": {
      "y_2014": 7.4336,
      "y_2015": 5.2181,
      "y_2017": 5.0523
    },
    "68": {
      "y_2014": 11.8596,
      "y_2015": 19.9516,
      "y_2017": 15.7725
    },
    "69": {
      "y_2014": 0.4127,
      "y_2015": 0.805,
      "y_2017": 1.0791
    },
    "70": {
      "y_2014": 50.159,
      "y_2015": 44.7925,
      "y_2017": 41.8803
    },
    "71": {
      "y_2014": 25.5763,
      "y_2015": 29.4641,
      "y_2017": 23.8301
    },
    "72": {
      "y_2014": 7.3563,
      "y_2015": 6.6884,
      "y_2017": 8.2483
    },
    "73": {
      "y_2014": 20.3237,
      "y_2015": 25.9194,
      "y_2017": 19.9932
    },
    "74": {
      "y_2014": 5.282,
      "y_2015": 7.7261,
      "y_2017": 8.971
    },
    "75": {
      "y_2014": 2.6861,
      "y_2015": 5.6824,
      "y_2017": 4.9292
    },
    "76": {
      "y_2014": 4.2596,
      "y_2015": 7.2659,
      "y_2017": 6.5782
    },
    "77": {
      "y_2014": 10.3199,
      "y_2015": 14.1494,
      "y_2017": 11.945
    },
    "78": {
      "y_2014": 8.7845,
      "y_2015": 15.1072,
      "y_2017": 12.6209
    },
    "79": {
      "y_2014": 25.986,
      "y_2015": 41.9113,
      "y_2017": 27.2807
    },
    "80": {
      "y_2014": 7.8591,
      "y_2015": 10.3825,
      "y_2017": 9.9188
    },
    "81": {
      "y_2014": 5.4422,
      "y_2015": 11.4796,
      "y_2017": 8.9478
    },
    "82": {
      "y_2014": 6.3341,
      "y_2015": 11.9952,
      "y_2017": 8.6127
    },
    "83": {
      "y_2014": 35.0588,
      "y_2015": 70.9906,
      "y_2017": 48.861
    },
    "84": {
      "y_2014": 9.7527,
      "y_2015": 11.6547,
      "y_2017": 14.0777
    },
    "85": {
      "y_2014": 44.5802,
      "y_2015": 52.4747,
      "y_2017": 46.7572
    },
    "86": {
      "y_2014": 26.9337,
      "y_2015": 31.1282,
      "y_2017": 22.7417
    },
    "87": {
      "y_2014": 47.482,
      "y_2015": 27.1903,
      "y_2017": 14.6635
    },
    "88": {
      "y_2014": 37.6857,
      "y_2015": 52.8442,
      "y_2017": 42.2187
    },
    "89": {
      "y_2014": 20.4394,
      "y_2015": 29.1313,
      "y_2017": 24.3839
    },
    "90": {
      "y_2014": 18.9436,
      "y_2015": 27.1407,
      "y_2017": 19.2615
    },
    "91": {
      "y_2014": 21.5703,
      "y_2015": 28.1743,
      "y_2017": 22.731
    },
    "92": {
      "y_2014": 4.2239,
      "y_2015": 7.3079,
      "y_2017": 8.1463
    },
    "93": {
      "y_2014": 20.2513,
      "y_2015": 26.5934,
      "y_2017": 20.3488
    },
    "94": {
      "y_2014": 25.0689,
      "y_2015": 35.8834,
      "y_2017": 28.9855
    },
    "95": {
      "y_2014": 10.0418,
      "y_2015": 13.7478,
      "y_2017": 14.8834
    },
    "96": {
      "y_2014": 12.522,
      "y_2015": 15.3324,
      "y_2017": 12.9548
    },
    "97": {
      "y_2014": 9.413,
      "y_2015": 10.1476,
      "y_2017": 9.5844
    },
    "98": {
      "y_2014": 15.5211,
      "y_2015": 23.9138,
      "y_2017": 20.4053
    },
    "99": {
      "y_2014": 14.9545,
      "y_2015": 22.0483,
      "y_2017": 16.5714
    },
    "100": {
      "y_2014": 28.2974,
      "y_2015": 40.6613,
      "y_2017": 32.0938
    },
    "101": {
      "y_2014": 31.2609,
      "y_2015": 33.6052,
      "y_2017": 26.2099
    },
    "102": {
      "y_2014": 25.7103,
      "y_2015": 30.0543,
      "y_2017": 26.0987
    },
    "103": {
      "y_2014": 39.1678,
      "y_2015": 39.8851,
      "y_2017": 37.3393
    },
    "105": {
      "y_2014": 14.161,
      "y_2015": 12.61,
      "y_2017": 8.1426
    },
    "106": {
      "y_2014": 25.1425,
      "y_2015": 26.3777,
      "y_2017": 24.3494
    },
    "107": {
      "y_2014": 27.9623,
      "y_2015": 22.3968,
      "y_2017": 25.4986
    },
    "108": {
      "y_2014": 25.297,
      "y_2015": 16.6435,
      "y_2017": 16.5738
    },
    "109": {
      "y_2014": 11.9792,
      "y_2015": 9.9593,
      "y_2017": 10.6712
    },
    "110": {
      "y_2014": 7.043,
      "y_2015": 8.731,
      "y_2017": 7.5401
    },
    "111": {
      "y_2014": 12.1884,
      "y_2015": 16.124,
      "y_2017": 19.8884
    },
    "112": {
      "y_2014": 14.5219,
      "y_2015": 21.7302,
      "y_2017": 15.3254
    },
    "113": {
      "y_2014": 18.1263,
      "y_2015": 27.0776,
      "y_2017": 22.2143
    },
    "114": {
      "y_2014": 30.5785,
      "y_2015": 38.2894,
      "y_2017": 35.24
    },
    "115": {
      "y_2014": 2.9813,
      "y_2015": 3.609,
      "y_2017": 3.6721
    },
    "116": {
      "y_2014": 30.3358,
      "y_2015": 28.8818,
      "y_2017": 21.0461
    },
    "117": {
      "y_2014": 20.4413,
      "y_2015": 29.6734,
      "y_2017": 22.4944
    },
    "118": {
      "y_2014": 4.0698,
      "y_2015": 3.958,
      "y_2017": 3.2609
    },
    "119": {
      "y_2014": 15.4478,
      "y_2015": 21.5657,
      "y_2017": 16.5326
    },
    "120": {
      "y_2014": 50.4395,
      "y_2015": 58.8079,
      "y_2017": 55.5928
    },
    "121": {
      "y_2014": 23.592,
      "y_2015": 35.8681,
      "y_2017": 29.6231
    },
    "122": {
      "y_2014": null,
      "y_2015": null,
      "y_2017": null
    },
    "123": {
      "y_2014": 28.5602,
      "y_2015": 33.7549,
      "y_2017": 31.0345
    },
    "124": {
      "y_2014": 29.5823,
      "y_2015": 40.5797,
      "y_2017": 34.4055
    },
    "125": {
      "y_2014": 29.1447,
      "y_2015": 39.0949,
      "y_2017": 26.3094
    },
    "126": {
      "y_2014": 71.7877,
      "y_2015": 42.4861,
      "y_2017": 45.3441
    },
    "127": {
      "y_2014": 28.7347,
      "y_2015": 34.5846,
      "y_2017": 31.177
    },
    "128": {
      "y_2014": 33.7421,
      "y_2015": 42.7433,
      "y_2017": 32.3776
    },
    "129": {
      "y_2014": 1.7865,
      "y_2015": 2.4248,
      "y_2017": 3.1939
    },
    "130": {
      "y_2014": 1.2871,
      "y_2015": 2.5996,
      "y_2017": 2.6997
    },
    "131": {
      "y_2014": 25,
      "y_2015": 16.6667,
      "y_2017": 14.6556
    },
    "132": {
      "y_2014": 3.6893,
      "y_2015": 5.293,
      "y_2017": 8.2218
    },
    "133": {
      "y_2014": 1.9626,
      "y_2015": 2.5926,
      "y_2017": 2.0314
    },
    "134": {
      "y_2014": 15.1888,
      "y_2015": 23.9617,
      "y_2017": 21.9937
    },
    "135": {
      "y_2014": 40.9486,
      "y_2015": 43.9252,
      "y_2017": 40.3633
    },
    "136": {
      "y_2014": 4.8205,
      "y_2015": 6.5425,
      "y_2017": 6.797
    },
    "137": {
      "y_2014": 64.4876,
      "y_2015": 45.3752,
      "y_2017": 32.7803
    },
    "138": {
      "y_2014": 22.7154,
      "y_2015": 35.9477,
      "y_2017": 36.9792
    },
    "139": {
      "y_2014": 24.1482,
      "y_2015": 32.2929,
      "y_2017": 25.461
    },
    "140": {
      "y_2014": 23.2116,
      "y_2015": 28.9242,
      "y_2017": 23.275
    },
    "141": {
      "y_2014": 29.3939,
      "y_2015": 42.5598,
      "y_2017": 34.0336
    },
    "142": {
      "y_2014": 18.2451,
      "y_2015": 27.0209,
      "y_2017": 21.0762
    },
    "143": {
      "y_2014": 2.1418,
      "y_2015": 2.5698,
      "y_2017": 2.4318
    },
    "144": {
      "y_2014": 29.3103,
      "y_2015": 36.5831,
      "y_2017": 31.8474
    },
    "145": {
      "y_2014": 29.934,
      "y_2015": 38.6431,
      "y_2017": 29.1667
    },
    "146": {
      "y_2014": 16.5198,
      "y_2015": 27.4772,
      "y_2017": 22.2504
    },
    "147": {
      "y_2014": 20.949,
      "y_2015": 29.4372,
      "y_2017": 26.7977
    },
    "148": {
      "y_2014": 2.2358,
      "y_2015": 2.7181,
      "y_2017": 2.2312
    },
    "149": {
      "y_2014": 5.4902,
      "y_2015": 6.8207,
      "y_2017": 5.7332
    },
    "150": {
      "y_2014": 19.3672,
      "y_2015": 30.1897,
      "y_2017": 22.8325
    },
    "151": {
      "y_2014": 3.5506,
      "y_2015": 6.25,
      "y_2017": 4.3599
    },
    "152": {
      "y_2014": 13.0967,
      "y_2015": 18.9356,
      "y_2017": 14.6402
    },
    "153": {
      "y_2014": 5.8342,
      "y_2015": 12.4104,
      "y_2017": 10.6878
    },
    "154": {
      "y_2014": 5.1844,
      "y_2015": 7.6181,
      "y_2017": 7.2782
    },
    "155": {
      "y_2014": 12.6531,
      "y_2015": 19.7173,
      "y_2017": 13.2867
    },
    "156": {
      "y_2014": 16.7323,
      "y_2015": 25.4386,
      "y_2017": 19.6641
    },
    "157": {
      "y_2014": 53.5406,
      "y_2015": 62.8478,
      "y_2017": 49.1473
    },
    "158": {
      "y_2014": 28.2977,
      "y_2015": 35.9759,
      "y_2017": 30.027
    },
    "159": {
      "y_2014": 40.0966,
      "y_2015": 55.2486,
      "y_2017": 42.8209
    },
    "160": {
      "y_2014": 30.1953,
      "y_2015": 39.5726,
      "y_2017": 34.6392
    },
    "161": {
      "y_2014": 13.7419,
      "y_2015": 22.2808,
      "y_2017": 17.3945
    },
    "162": {
      "y_2014": 25.4317,
      "y_2015": 33.0412,
      "y_2017": 24.7824
    },
    "163": {
      "y_2014": 22.3256,
      "y_2015": 20.51,
      "y_2017": 15.3163
    },
    "164": {
      "y_2014": 25.8936,
      "y_2015": 38.2819,
      "y_2017": 31.4304
    },
    "165": {
      "y_2014": 35.8943,
      "y_2015": 35.2822,
      "y_2017": 29.3069
    },
    "166": {
      "y_2014": 26.5273,
      "y_2015": 32.7287,
      "y_2017": 30.3221
    },
    "167": {
      "y_2014": 25.8186,
      "y_2015": 30.8168,
      "y_2017": 25.1549
    },
    "168": {
      "y_2014": 27.6433,
      "y_2015": 34.2138,
      "y_2017": 28.598
    },
    "169": {
      "y_2014": 3.3113,
      "y_2015": 6.0703,
      "y_2017": 5.5427
    },
    "170": {
      "y_2014": 2.4631,
      "y_2015": 4.3099,
      "y_2017": 4.918
    },
    "171": {
      "y_2014": 4.281,
      "y_2015": 4.4494,
      "y_2017": 3.6649
    },
    "172": {
      "y_2014": 2.7967,
      "y_2015": 4.7355,
      "y_2017": 4.4017
    },
    "173": {
      "y_2014": 35.4749,
      "y_2015": 41.3252,
      "y_2017": 32.1341
    },
    "174": {
      "y_2014": 13.0485,
      "y_2015": 17.7597,
      "y_2017": 15.9698
    },
    "175": {
      "y_2014": 1.9857,
      "y_2015": 3.4973,
      "y_2017": 3.7788
    },
    "176": {
      "y_2014": 2.3739,
      "y_2015": 3.8905,
      "y_2017": 3.8576
    },
    "177": {
      "y_2014": 13.7912,
      "y_2015": 6.5241,
      "y_2017": 12.1292
    },
    "178": {
      "y_2014": 2.7436,
      "y_2015": 5.3887,
      "y_2017": 7.0175
    },
    "179": {
      "y_2014": 12.5232,
      "y_2015": 6.2924,
      "y_2017": 6.203
    },
    "180": {
      "y_2014": 22.8462,
      "y_2015": 32.7801,
      "y_2017": 25.4876
    },
    "181": {
      "y_2014": 3.3692,
      "y_2015": 3.8743,
      "y_2017": 3.0871
    },
    "182": {
      "y_2014": 35.9435,
      "y_2015": 41.8485,
      "y_2017": 36.2832
    },
    "183": {
      "y_2014": 22.1698,
      "y_2015": 31.3003,
      "y_2017": 24.7423
    },
    "184": {
      "y_2014": 1.8643,
      "y_2015": 3.2871,
      "y_2017": 2.5641
    },
    "185": {
      "y_2014": 11.081,
      "y_2015": 19.054,
      "y_2017": 16.6884
    },
    "186": {
      "y_2014": 22.594,
      "y_2015": 29.8544,
      "y_2017": 22.4124
    },
    "187": {
      "y_2014": 3.9841,
      "y_2015": 8.5657,
      "y_2017": 5.1793
    },
    "188": {
      "y_2014": 2.6675,
      "y_2015": 4.7674,
      "y_2017": 4.1279
    },
    "189": {
      "y_2014": 5.7617,
      "y_2015": 9.4727,
      "y_2017": 6.6406
    },
    "190": {
      "y_2014": 33.0116,
      "y_2015": 43.1579,
      "y_2017": 36.6603
    },
    "191": {
      "y_2014": 7.152,
      "y_2015": 12.3619,
      "y_2017": 9.8147
    },
    "192": {
      "y_2014": 14.622,
      "y_2015": 21.8828,
      "y_2017": 16.6667
    },
    "193": {
      "y_2014": 8.4274,
      "y_2015": 9.5417,
      "y_2017": 7.2289
    },
    "194": {
      "y_2014": 2.1212,
      "y_2015": 2.7806,
      "y_2017": 2.9431
    },
    "195": {
      "y_2014": 10.5742,
      "y_2015": 16.5865,
      "y_2017": 12.3774
    },
    "196": {
      "y_2014": 16.235,
      "y_2015": 26.7426,
      "y_2017": 19.132
    },
    "197": {
      "y_2014": 23.2038,
      "y_2015": 30.5052,
      "y_2017": 27.3498
    },
    "198": {
      "y_2014": 2.4938,
      "y_2015": 6.8085,
      "y_2017": 8.8366
    },
    "199": {
      "y_2014": 36.3636,
      "y_2015": 47.0645,
      "y_2017": 37.3709
    },
    "200": {
      "y_2014": 77.6801,
      "y_2015": 63.9073,
      "y_2017": 31.694
    },
    "201": {
      "y_2014": 1.3425,
      "y_2015": 3.3881,
      "y_2017": 2.9703
    },
    "202": {
      "y_2014": 32.19,
      "y_2015": 41.5457,
      "y_2017": 31.9356
    },
    "203": {
      "y_2014": 10.1704,
      "y_2015": 17.1215,
      "y_2017": 12.3876
    },
    "204": {
      "y_2014": 2.3741,
      "y_2015": 3.8129,
      "y_2017": 3.6628
    },
    "205": {
      "y_2014": null,
      "y_2015": 1.2739,
      "y_2017": 0.7239
    },
    "206": {
      "y_2014": 1.9217,
      "y_2015": 2.2912,
      "y_2017": 3.3333
    },
    "207": {
      "y_2014": 2.1087,
      "y_2015": 7.8896,
      "y_2017": 8.0805
    },
    "208": {
      "y_2014": 0.4371,
      "y_2015": 0.7261,
      "y_2017": 0.2842
    },
    "209": {
      "y_2014": 15.5609,
      "y_2015": 21.598,
      "y_2017": 14.4879
    },
    "210": {
      "y_2014": 8.1458,
      "y_2015": 5.8635,
      "y_2017": 5.8587
    },
    "211": {
      "y_2014": 14.5866,
      "y_2015": 24.3222,
      "y_2017": 17.2374
    },
    "212": {
      "y_2014": 33.3819,
      "y_2015": 40.6475,
      "y_2017": 36.3245
    },
    "213": {
      "y_2014": 2.9059,
      "y_2015": 3.4569,
      "y_2017": 1.9868
    },
    "215": {
      "y_2014": null,
      "y_2015": null,
      "y_2017": null
    },
    "216": {
      "y_2014": 1.1125,
      "y_2015": 1.7199,
      "y_2017": 1.6311
    },
    "217": {
      "y_2014": 0.5538,
      "y_2015": 1.1592,
      "y_2017": 0.7359
    },
    "218": {
      "y_2014": 9.801,
      "y_2015": 12.9068,
      "y_2017": 16.7952
    },
    "219": {
      "y_2014": 8.101,
      "y_2015": 12.5783,
      "y_2017": 9.61
    },
    "220": {
      "y_2014": 20.1599,
      "y_2015": 25.9887,
      "y_2017": 18.0743
    },
    "221": {
      "y_2014": 10.3358,
      "y_2015": 19.2609,
      "y_2017": 14.9557
    },
    "222": {
      "y_2014": 1.5833,
      "y_2015": 2.0926,
      "y_2017": 2.1916
    },
    "223": {
      "y_2014": 27.588,
      "y_2015": 31.7073,
      "y_2017": 26.2182
    },
    "224": {
      "y_2014": 5.1315,
      "y_2015": 7.7184,
      "y_2017": 7.5488
    },
    "225": {
      "y_2014": 8.0741,
      "y_2015": 13.7269,
      "y_2017": 11.2554
    },
    "226": {
      "y_2014": 4.6243,
      "y_2015": 5.4023,
      "y_2017": 4.811
    },
    "227": {
      "y_2014": 15.3355,
      "y_2015": 22.663,
      "y_2017": 18.2715
    },
    "228": {
      "y_2014": 17.0686,
      "y_2015": 21.6514,
      "y_2017": 22.7523
    },
    "229": {
      "y_2014": 34.7386,
      "y_2015": 50.3955,
      "y_2017": 38.3918
    },
    "230": {
      "y_2014": 13.2303,
      "y_2015": 13.6085,
      "y_2017": 11.0069
    },
    "231": {
      "y_2014": 7.9391,
      "y_2015": 8.5405,
      "y_2017": 9.299
    },
    "232": {
      "y_2014": 12.766,
      "y_2015": 17.1686,
      "y_2017": 13.0467
    },
    "233": {
      "y_2014": 2.0328,
      "y_2015": 5.5164,
      "y_2017": 4.9
    },
    "234": {
      "y_2014": 41.3955,
      "y_2015": 43.6738,
      "y_2017": 34.6356
    },
    "235": {
      "y_2014": 3.3252,
      "y_2015": 3.4934,
      "y_2017": 3.6267
    },
    "236": {
      "y_2014": 1.272,
      "y_2015": 1.0377,
      "y_2017": 0.6616
    },
    "237": {
      "y_2014": 24.0734,
      "y_2015": 31.018,
      "y_2017": 25.9069
    },
    "238": {
      "y_2014": 22.0757,
      "y_2015": 31.0374,
      "y_2017": 23.6478
    },
    "240": {
      "y_2014": 13.2064,
      "y_2015": 18.7919,
      "y_2017": 14.7748
    },
    "241": {
      "y_2014": 0.7396,
      "y_2015": 1.0972,
      "y_2017": 0.9356
    },
    "242": {
      "y_2014": 15.3656,
      "y_2015": 20.9816,
      "y_2017": 16.9277
    },
    "243": {
      "y_2014": 17.4603,
      "y_2015": 13.7097,
      "y_2017": 8.871
    },
    "244": {
      "y_2014": 12.8697,
      "y_2015": 17.9554,
      "y_2017": 18.4033
    },
    "245": {
      "y_2014": 25.0532,
      "y_2015": 34.1737,
      "y_2017": 28.0445
    },
    "246": {
      "y_2014": 19.8639,
      "y_2015": 28.3375,
      "y_2017": 21.0351
    },
    "247": {
      "y_2014": 37.0337,
      "y_2015": 39.6853,
      "y_2017": 31.4879
    },
    "248": {
      "y_2014": 15.9843,
      "y_2015": 22.2591,
      "y_2017": 24.546
    },
    "249": {
      "y_2014": 35.3085,
      "y_2015": 40.7808,
      "y_2017": 26.8585
    },
    "250": {
      "y_2014": 9.1599,
      "y_2015": 11.5765,
      "y_2017": 9.6568
    },
    "251": {
      "y_2014": 9.0154,
      "y_2015": 14.6556,
      "y_2017": 10.3804
    },
    "252": {
      "y_2014": 2.8791,
      "y_2015": 5.2834,
      "y_2017": 6.2141
    },
    "253": {
      "y_2014": 2.7805,
      "y_2015": 3.7524,
      "y_2017": 2.8752
    },
    "254": {
      "y_2014": 13.9194,
      "y_2015": 9.7786,
      "y_2017": 4.845
    },
    "255": {
      "y_2014": 2.038,
      "y_2015": 3.5233,
      "y_2017": 3.1779
    },
    "256": {
      "y_2014": 1.5412,
      "y_2015": 3.087,
      "y_2017": 3.2512
    },
    "257": {
      "y_2014": 4.7856,
      "y_2015": 7.848,
      "y_2017": 6.1618
    },
    "258": {
      "y_2014": 32.9315,
      "y_2015": 32.1149,
      "y_2017": 25.2025
    },
    "259": {
      "y_2014": 19.8144,
      "y_2015": 28.3708,
      "y_2017": 20.0961
    },
    "260": {
      "y_2014": 19.0975,
      "y_2015": 25.8013,
      "y_2017": 20.4835
    },
    "261": {
      "y_2014": 7.9642,
      "y_2015": 11.7547,
      "y_2017": 8.2943
    },
    "262": {
      "y_2014": 1.3371,
      "y_2015": 2.8607,
      "y_2017": 2.5792
    },
    "263": {
      "y_2014": 2.1748,
      "y_2015": 3.3763,
      "y_2017": 2.5065
    },
    "264": {
      "y_2014": 8.9679,
      "y_2015": 14.7722,
      "y_2017": 13.3053
    },
    "265": {
      "y_2014": 7.291,
      "y_2015": 13.4358,
      "y_2017": 10.6738
    },
    "266": {
      "y_2014": 8.6063,
      "y_2015": 13.4495,
      "y_2017": 11.4825
    },
    "267": {
      "y_2014": 8.6136,
      "y_2015": 11.9058,
      "y_2017": 9.5258
    },
    "268": {
      "y_2014": 20.3756,
      "y_2015": 29.0828,
      "y_2017": 25.5556
    },
    "269": {
      "y_2014": 4.8306,
      "y_2015": 5.9119,
      "y_2017": 5.3533
    },
    "270": {
      "y_2014": 23.9766,
      "y_2015": 32.7325,
      "y_2017": 31.0394
    },
    "271": {
      "y_2014": 29.024,
      "y_2015": 38.1939,
      "y_2017": 33.2245
    },
    "272": {
      "y_2014": 15.0345,
      "y_2015": 21.7931,
      "y_2017": 20.8276
    },
    "273": {
      "y_2014": 12.2346,
      "y_2015": 18.3663,
      "y_2017": 16.7375
    },
    "274": {
      "y_2014": 8.1809,
      "y_2015": 12.0722,
      "y_2017": 12.3928
    },
    "275": {
      "y_2014": 8.1478,
      "y_2015": 11.3787,
      "y_2017": 10.2698
    },
    "276": {
      "y_2014": 6.9001,
      "y_2015": 10.4008,
      "y_2017": 9.4732
    },
    "277": {
      "y_2014": 9.4364,
      "y_2015": 12.6526,
      "y_2017": 7.6887
    },
    "278": {
      "y_2014": 8.1875,
      "y_2015": 12.7965,
      "y_2017": 12.5468
    },
    "279": {
      "y_2014": 5.4485,
      "y_2015": 10.299,
      "y_2017": 9.2359
    },
    "280": {
      "y_2014": 48.2043,
      "y_2015": 60.5016,
      "y_2017": 44.4357
    },
    "281": {
      "y_2014": 9.5595,
      "y_2015": 18.2755,
      "y_2017": 18.8379
    },
    "282": {
      "y_2014": 15.0285,
      "y_2015": 23.0028,
      "y_2017": 21.3731
    },
    "283": {
      "y_2014": 17.2335,
      "y_2015": 22.1386,
      "y_2017": 19.8276
    },
    "284": {
      "y_2014": 0.6198,
      "y_2015": 1.4583,
      "y_2017": 1.4213
    },
    "285": {
      "y_2014": null,
      "y_2015": null,
      "y_2017": null
    },
    "286": {
      "y_2014": null,
      "y_2015": null,
      "y_2017": null
    },
    "287": {
      "y_2014": 15.4684,
      "y_2015": 16.4931,
      "y_2017": 14.1589
    },
    "288": {
      "y_2014": 4.4675,
      "y_2015": 4.5778,
      "y_2017": 4.2977
    },
    "289": {
      "y_2014": 7.1409,
      "y_2015": 12.0087,
      "y_2017": 10.0644
    },
    "290": {
      "y_2014": 74.2481,
      "y_2015": 25.2289,
      "y_2017": 20.555
    },
    "291": {
      "y_2014": 31.4081,
      "y_2015": 37.696,
      "y_2017": 34.106
    },
    "292": {
      "y_2014": 40.222,
      "y_2015": 49.2958,
      "y_2017": 43.5398
    },
    "293": {
      "y_2014": 35.3081,
      "y_2015": 54.6229,
      "y_2017": 40.0673
    },
    "294": {
      "y_2014": 36.1895,
      "y_2015": 48.7052,
      "y_2017": 43.8393
    },
    "295": {
      "y_2014": 35.9495,
      "y_2015": 44.8664,
      "y_2017": 39.548
    },
    "296": {
      "y_2014": 8.8496,
      "y_2015": 15.7962,
      "y_2017": 11.8848
    },
    "297": {
      "y_2014": 1.8141,
      "y_2015": 1.5556,
      "y_2017": null
    },
    "298": {
      "y_2014": 13.9643,
      "y_2015": 18.0132,
      "y_2017": 18.5039
    },
    "299": {
      "y_2014": 14.5418,
      "y_2015": 21.9441,
      "y_2017": 16.6515
    },
    "300": {
      "y_2014": 17.035,
      "y_2015": 13.2719,
      "y_2017": 12.0658
    },
    "301": {
      "y_2014": 12.4468,
      "y_2015": 17.5634,
      "y_2017": 12.5314
    },
    "302": {
      "y_2014": 7.7785,
      "y_2015": 10.02,
      "y_2017": 8.0363
    },
    "303": {
      "y_2014": 9.7479,
      "y_2015": 15.9645,
      "y_2017": 13.171
    },
    "304": {
      "y_2014": 33.4711,
      "y_2015": 38.0259,
      "y_2017": 29.17
    },
    "305": {
      "y_2014": 17.0068,
      "y_2015": 26.1161,
      "y_2017": 22.2595
    },
    "306": {
      "y_2014": 75.739,
      "y_2015": 54.7226,
      "y_2017": 43.9279
    },
    "307": {
      "y_2014": 18.2157,
      "y_2015": 26.5141,
      "y_2017": 16.4492
    },
    "308": {
      "y_2014": 3.6458,
      "y_2015": 4.0253,
      "y_2017": 3.6306
    },
    "309": {
      "y_2014": 5.6005,
      "y_2015": 5.4994,
      "y_2017": 5.097
    },
    "310": {
      "y_2014": 6.1114,
      "y_2015": 7.7512,
      "y_2017": 6.912
    },
    "311": {
      "y_2014": 31.0539,
      "y_2015": 39.0304,
      "y_2017": 33.0645
    },
    "312": {
      "y_2014": 34.3249,
      "y_2015": 43.1869,
      "y_2017": 35.0423
    },
    "313": {
      "y_2014": 19.1247,
      "y_2015": 26.0791,
      "y_2017": 19.7842
    },
    "314": {
      "y_2014": 35.4631,
      "y_2015": 36.0619,
      "y_2017": 25.5157
    },
    "315": {
      "y_2014": 2.946,
      "y_2015": 3.3738,
      "y_2017": 4.8748
    },
    "316": {
      "y_2014": 31.4346,
      "y_2015": 32.9034,
      "y_2017": 26.3524
    },
    "317": {
      "y_2014": 42.2194,
      "y_2015": 54.5113,
      "y_2017": 47.6427
    },
    "318": {
      "y_2014": 3.3113,
      "y_2015": 5.7831,
      "y_2017": 9.2432
    },
    "319": {
      "y_2014": 17.9645,
      "y_2015": 23.4796,
      "y_2017": 19.065
    },
    "320": {
      "y_2014": 11.6992,
      "y_2015": 7.4039,
      "y_2017": 2.8311
    },
    "321": {
      "y_2014": 39.8607,
      "y_2015": 46.8803,
      "y_2017": 44.1569
    },
    "322": {
      "y_2014": 22.1447,
      "y_2015": 28.6187,
      "y_2017": 21.5578
    },
    "323": {
      "y_2014": 26.4682,
      "y_2015": 33.5895,
      "y_2017": 26.3761
    },
    "324": {
      "y_2014": 8.8058,
      "y_2015": 9.7532,
      "y_2017": 8.6279
    },
    "325": {
      "y_2014": 15.2158,
      "y_2015": 24.0203,
      "y_2017": 22.6849
    },
    "326": {
      "y_2014": 41.258,
      "y_2015": 40.0417,
      "y_2017": 37.2917
    },
    "327": {
      "y_2014": 40.9496,
      "y_2015": 48.7119,
      "y_2017": 40.2907
    },
    "328": {
      "y_2014": 30.6496,
      "y_2015": 30.5732,
      "y_2017": 34.2153
    },
    "329": {
      "y_2014": 15.2163,
      "y_2015": 21.5705,
      "y_2017": 19.2123
    },
    "330": {
      "y_2014": 16.8162,
      "y_2015": 26.9428,
      "y_2017": 19.8932
    },
    "331": {
      "y_2014": 7.7162,
      "y_2015": 11.4409,
      "y_2017": 11.7362
    },
    "332": {
      "y_2014": 15.6442,
      "y_2015": 22.1029,
      "y_2017": 14.3239
    },
    "333": {
      "y_2014": 24.3149,
      "y_2015": 32.2068,
      "y_2017": 23.6542
    },
    "334": {
      "y_2014": 1.897,
      "y_2015": 4.0431,
      "y_2017": 1.7473
    },
    "335": {
      "y_2014": 8.7552,
      "y_2015": 7.2804,
      "y_2017": 6.2978
    },
    "336": {
      "y_2014": 7.719,
      "y_2015": 13.6029,
      "y_2017": 11.0112
    },
    "337": {
      "y_2014": 4.1882,
      "y_2015": 7.7875,
      "y_2017": 6.9756
    },
    "338": {
      "y_2014": 17.4238,
      "y_2015": 18.5921,
      "y_2017": 12.1366
    },
    "339": {
      "y_2014": 1.1494,
      "y_2015": 0.5714,
      "y_2017": 0.6257
    },
    "340": {
      "y_2014": 22.9065,
      "y_2015": 12.6676,
      "y_2017": 15.6394
    },
    "341": {
      "y_2014": 26.5633,
      "y_2015": 14.3743,
      "y_2017": 14.0116
    },
    "342": {
      "y_2014": 5.1625,
      "y_2015": null,
      "y_2017": null
    },
    "343": {
      "y_2014": 6.8866,
      "y_2015": 11.0012,
      "y_2017": 7.9732
    },
    "344": {
      "y_2014": 12.1131,
      "y_2015": 15.3659,
      "y_2017": 13.1564
    },
    "345": {
      "y_2014": 15.9655,
      "y_2015": 23.9014,
      "y_2017": 16.9329
    },
    "346": {
      "y_2014": 29.5269,
      "y_2015": 37.6842,
      "y_2017": 29.9204
    },
    "347": {
      "y_2014": 28.4848,
      "y_2015": 26.0417,
      "y_2017": 21.1251
    },
    "348": {
      "y_2014": 12.6814,
      "y_2015": 17.25,
      "y_2017": 15.8951
    },
    "349": {
      "y_2014": 9.2408,
      "y_2015": 10.5419,
      "y_2017": 5.7372
    },
    "350": {
      "y_2014": 1.6036,
      "y_2015": 3.1626,
      "y_2017": 2.5983
    },
    "351": {
      "y_2014": 9.6066,
      "y_2015": 10.6578,
      "y_2017": 7.5856
    },
    "352": {
      "y_2014": 3.8415,
      "y_2015": 8.1967,
      "y_2017": 6.6373
    },
    "353": {
      "y_2014": 2.6254,
      "y_2015": 4.2146,
      "y_2017": 3.1478
    },
    "354": {
      "y_2014": 4.2434,
      "y_2015": 6.4768,
      "y_2017": 5.6951
    },
    "355": {
      "y_2014": 2.3124,
      "y_2015": 2.9731,
      "y_2017": 3.6338
    },
    "356": {
      "y_2014": 1.5189,
      "y_2015": 2.3005,
      "y_2017": 2.4526
    },
    "357": {
      "y_2014": 8.6721,
      "y_2015": 8.5597,
      "y_2017": 9.478
    },
    "358": {
      "y_2014": 1.7019,
      "y_2015": 2.7474,
      "y_2017": 3.5105
    },
    "359": {
      "y_2014": 1.8708,
      "y_2015": 2.087,
      "y_2017": 1.5514
    },
    "360": {
      "y_2014": 13.1915,
      "y_2015": 18.5623,
      "y_2017": 15.2301
    },
    "361": {
      "y_2014": 33.363,
      "y_2015": 51.0526,
      "y_2017": 20.3363
    },
    "362": {
      "y_2014": 37.7792,
      "y_2015": 45.446,
      "y_2017": 41.5638
    },
    "363": {
      "y_2014": 37.0192,
      "y_2015": 43.512,
      "y_2017": 41.0732
    },
    "364": {
      "y_2014": 0.4372,
      "y_2015": 0.2454,
      "y_2017": 0.487
    },
    "365": {
      "y_2014": 13.3374,
      "y_2015": 18.3867,
      "y_2017": 13.8235
    },
    "366": {
      "y_2014": 17.3442,
      "y_2015": 21.7337,
      "y_2017": 18.4949
    },
    "367": {
      "y_2014": 4.878,
      "y_2015": 4.4801,
      "y_2017": 3.5277
    },
    "368": {
      "y_2014": 14.187,
      "y_2015": 18.8611,
      "y_2017": 15.5036
    },
    "369": {
      "y_2014": 41.9228,
      "y_2015": 55.3816,
      "y_2017": 41.4788
    },
    "370": {
      "y_2014": 94.3204,
      "y_2015": 63.207,
      "y_2017": 72.4191
    },
    "371": {
      "y_2014": 31.8647,
      "y_2015": 41.8842,
      "y_2017": 36.0964
    },
    "372": {
      "y_2014": 3.8484,
      "y_2015": 6.4097,
      "y_2017": 5.1095
    },
    "373": {
      "y_2014": 1.6,
      "y_2015": 2.9845,
      "y_2017": 3.1765
    },
    "374": {
      "y_2014": 32.7427,
      "y_2015": 47.4869,
      "y_2017": 44.8181
    },
    "375": {
      "y_2014": 0.5061,
      "y_2015": 0.9163,
      "y_2017": 0.9555
    },
    "376": {
      "y_2014": 9.9746,
      "y_2015": 15.97,
      "y_2017": 12.7316
    },
    "377": {
      "y_2014": 9.0018,
      "y_2015": 15.6747,
      "y_2017": 12.2205
    },
    "378": {
      "y_2014": 3.6617,
      "y_2015": 4.1379,
      "y_2017": 3.1478
    },
    "379": {
      "y_2014": 0.625,
      "y_2015": 1.1423,
      "y_2017": 1.0482
    },
    "380": {
      "y_2014": 1.2807,
      "y_2015": 2.1656,
      "y_2017": 2.0038
    },
    "381": {
      "y_2014": 8.3686,
      "y_2015": 11.0931,
      "y_2017": 8.8807
    },
    "382": {
      "y_2014": 21.9237,
      "y_2015": 25.8361,
      "y_2017": 22.7621
    },
    "383": {
      "y_2014": 18.0525,
      "y_2015": 23.9433,
      "y_2017": 17.5121
    },
    "384": {
      "y_2014": 3.7796,
      "y_2015": 3.1139,
      "y_2017": 2.6424
    },
    "385": {
      "y_2014": 44.1547,
      "y_2015": 50.53,
      "y_2017": 43.1297
    },
    "386": {
      "y_2014": 22.1812,
      "y_2015": 24.1944,
      "y_2017": 20.2083
    },
    "387": {
      "y_2014": 43.7336,
      "y_2015": 53.2445,
      "y_2017": 48.2878
    },
    "388": {
      "y_2014": 16.4931,
      "y_2015": 15.2947,
      "y_2017": 8.1445
    },
    "389": {
      "y_2014": 24.8357,
      "y_2015": 28.0051,
      "y_2017": 22.719
    },
    "390": {
      "y_2014": 13.5593,
      "y_2015": 21.7302,
      "y_2017": 17.6431
    },
    "391": {
      "y_2014": 3.9405,
      "y_2015": 5.3663,
      "y_2017": 4.4236
    },
    "392": {
      "y_2014": 0.9651,
      "y_2015": 1.5596,
      "y_2017": 1.3435
    },
    "393": {
      "y_2014": 7.5038,
      "y_2015": 8.6213,
      "y_2017": 8.5266
    },
    "394": {
      "y_2014": 11.8668,
      "y_2015": 19.2164,
      "y_2017": 16.9283
    },
    "395": {
      "y_2014": 13.2015,
      "y_2015": 8.5443,
      "y_2017": 9.4125
    },
    "396": {
      "y_2014": 9.6629,
      "y_2015": 13.2627,
      "y_2017": 10.0867
    },
    "397": {
      "y_2014": 5.811,
      "y_2015": 4.7129,
      "y_2017": 4.3841
    },
    "398": {
      "y_2014": 4.2517,
      "y_2015": 4.9767,
      "y_2017": 4.9491
    },
    "399": {
      "y_2014": 5.3439,
      "y_2015": 4.579,
      "y_2017": 4.2783
    },
    "400": {
      "y_2014": 2.5337,
      "y_2015": 2.2943,
      "y_2017": 2.5257
    },
    "401": {
      "y_2014": 27.6099,
      "y_2015": 10.1873,
      "y_2017": 10.8269
    },
    "402": {
      "y_2014": 7.1429,
      "y_2015": 5.6818,
      "y_2017": 5.3662
    },
    "403": {
      "y_2014": 6.4331,
      "y_2015": 5.864,
      "y_2017": 4.5409
    },
    "404": {
      "y_2014": 26.3815,
      "y_2015": 17.5447,
      "y_2017": 12.8908
    },
    "405": {
      "y_2014": 10.5491,
      "y_2015": 6.4767,
      "y_2017": 5.6403
    },
    "406": {
      "y_2014": 7.6,
      "y_2015": 6.6636,
      "y_2017": 4.6922
    },
    "407": {
      "y_2014": 10.6291,
      "y_2015": 9.8448,
      "y_2017": 8.4896
    },
    "408": {
      "y_2014": 5.0558,
      "y_2015": 5.8607,
      "y_2017": 7.3626
    },
    "409": {
      "y_2014": 1.0823,
      "y_2015": 1.4154,
      "y_2017": 1.4716
    },
    "410": {
      "y_2014": 3.1395,
      "y_2015": 3.7835,
      "y_2017": 2.5029
    },
    "411": {
      "y_2014": 14.9418,
      "y_2015": 10.5701,
      "y_2017": 8.8046
    },
    "412": {
      "y_2014": 6.8807,
      "y_2015": 4.3478,
      "y_2017": 2.963
    },
    "413": {
      "y_2014": 3.7319,
      "y_2015": 2.7112,
      "y_2017": 2.136
    },
    "416": {
      "y_2014": 5.6,
      "y_2015": 7.0154,
      "y_2017": 7.2
    },
    "417": {
      "y_2014": 12.8788,
      "y_2015": 8.3333,
      "y_2017": 7.5796
    },
    "418": {
      "y_2014": 4.0798,
      "y_2015": 4.1402,
      "y_2017": 4.2007
    },
    "419": {
      "y_2014": 1.2928,
      "y_2015": 1.1624,
      "y_2017": 1.0655
    },
    "420": {
      "y_2014": 4.9924,
      "y_2015": 4.1161,
      "y_2017": 3.2058
    },
    "421": {
      "y_2014": 5.1724,
      "y_2015": 4.7915,
      "y_2017": 3.5184
    },
    "422": {
      "y_2014": 39.3421,
      "y_2015": 20.0188,
      "y_2017": 17.698
    },
    "423": {
      "y_2014": 7.3947,
      "y_2015": 7.4699,
      "y_2017": 5.7289
    },
    "424": {
      "y_2014": 1.5385,
      "y_2015": 1.717,
      "y_2017": 2.179
    },
    "425": {
      "y_2014": 3.8206,
      "y_2015": 3.4682,
      "y_2017": 3.4591
    },
    "426": {
      "y_2014": 11.6756,
      "y_2015": 10.22,
      "y_2017": 8.3741
    },
    "428": {
      "y_2014": 17.1209,
      "y_2015": 20.2927,
      "y_2017": 17.1143
    },
    "430": {
      "y_2014": 27.0117,
      "y_2015": 22.7887,
      "y_2017": 19.6758
    },
    "431": {
      "y_2014": 16.1148,
      "y_2015": 15.867,
      "y_2017": 13.0667
    },
    "432": {
      "y_2014": 11.7279,
      "y_2015": 9.9348,
      "y_2017": 7.6865
    },
    "433": {
      "y_2014": 4.5817,
      "y_2015": 2.988,
      "y_2017": 1.7804
    },
    "434": {
      "y_2014": 5.6942,
      "y_2015": 3.7292,
      "y_2017": 2.4461
    },
    "435": {
      "y_2014": 8.4507,
      "y_2015": 6.5898,
      "y_2017": 5.9937
    },
    "436": {
      "y_2014": 14.5807,
      "y_2015": 16.0424,
      "y_2017": 14.8883
    },
    "437": {
      "y_2014": 15.366,
      "y_2015": 9.1833,
      "y_2017": 8.5775
    },
    "438": {
      "y_2014": 11.8876,
      "y_2015": 6.7961,
      "y_2017": 4.2831
    },
    "442": {
      "y_2014": 16.1111,
      "y_2015": 23.1532,
      "y_2017": 20.1149
    },
    "443": {
      "y_2014": 9.8888,
      "y_2015": 6.0712,
      "y_2017": 7.4854
    },
    "444": {
      "y_2014": 23.7646,
      "y_2015": 16.8454,
      "y_2017": 13.3862
    },
    "445": {
      "y_2014": 5.548,
      "y_2015": 5.1107,
      "y_2017": 3.9823
    },
    "446": {
      "y_2014": 12.3089,
      "y_2015": 9.5448,
      "y_2017": 6.5427
    },
    "447": {
      "y_2014": 6.3243,
      "y_2015": 6.7109,
      "y_2017": 4.7745
    },
    "448": {
      "y_2014": 5.0701,
      "y_2015": 5.7875,
      "y_2017": 4.9732
    },
    "449": {
      "y_2014": 1.1956,
      "y_2015": 1.1504,
      "y_2017": 1.3191
    },
    "450": {
      "y_2014": 3.9158,
      "y_2015": 3.268,
      "y_2017": 2.9197
    },
    "451": {
      "y_2014": null,
      "y_2015": null,
      "y_2017": null
    },
    "452": {
      "y_2014": 6.4237,
      "y_2015": 7.929,
      "y_2017": 10.4425
    },
    "453": {
      "y_2014": 31.3716,
      "y_2015": 19.5012,
      "y_2017": 15.1772
    },
    "454": {
      "y_2014": 6.0606,
      "y_2015": 4.6958,
      "y_2017": 5.1519
    },
    "455": {
      "y_2014": 4.9799,
      "y_2015": 6.7907,
      "y_2017": 4.6625
    },
    "456": {
      "y_2014": 16.3934,
      "y_2015": 11.4075,
      "y_2017": 20.3468
    },
    "457": {
      "y_2014": 3.2136,
      "y_2015": 2.7488,
      "y_2017": 2.8275
    },
    "458": {
      "y_2014": 8.1633,
      "y_2015": 6.1279,
      "y_2017": 3.5492
    },
    "459": {
      "y_2014": 13.71,
      "y_2015": 11.4789,
      "y_2017": 9.6438
    },
    "460": {
      "y_2014": 13.8467,
      "y_2015": 12.4875,
      "y_2017": 10.6773
    },
    "462": {
      "y_2014": 20.4142,
      "y_2015": 12.1311,
      "y_2017": 6.592
    },
    "463": {
      "y_2014": 19.9158,
      "y_2015": 16.6039,
      "y_2017": 14.4201
    },
    "464": {
      "y_2014": 4.0091,
      "y_2015": 3.1145,
      "y_2017": 2.0937
    },
    "465": {
      "y_2014": 18.3706,
      "y_2015": 10.3834,
      "y_2017": 8.0671
    },
    "466": {
      "y_2014": 13.7356,
      "y_2015": 11.7877,
      "y_2017": 9.1536
    },
    "467": {
      "y_2014": 5.7924,
      "y_2015": 5.2291,
      "y_2017": 4.7509
    },
    "468": {
      "y_2014": null,
      "y_2015": null,
      "y_2017": null
    },
    "469": {
      "y_2014": null,
      "y_2015": null,
      "y_2017": null
    },
    "470": {
      "y_2014": 0.8127,
      "y_2015": 1.8408,
      "y_2017": 1.8353
    },
    "471": {
      "y_2014": 7.31,
      "y_2015": 7.0011,
      "y_2017": 5.842
    },
    "472": {
      "y_2014": 3.6434,
      "y_2015": 2.4427,
      "y_2017": 1.8699
    },
    "473": {
      "y_2014": null,
      "y_2015": null,
      "y_2017": null
    },
    "474": {
      "y_2014": 4.576,
      "y_2015": 3.0544,
      "y_2017": 4.413
    },
    "475": {
      "y_2014": null,
      "y_2015": null,
      "y_2017": null
    }
  }
}